Workbook

Sheet 使用說明
A1: 類別 | B1: 說明
A2: 資料狀態 | B2: ★ 本檔所有營業額、成本、來客數、品項銷量均為程式模擬產生，非實際營運數字。
A3: 資料狀態 | B3: ★ 門市名稱、店型、租金、座位數亦為假設值，請以貴公司 POS / 會計 / 人資系統實際資料覆蓋。
A4: 涵蓋範圍 | B4: ★ 資料期間為 2024-01 至 2026-09，共 33 個月；2026 年為年初至 9 月（YTD），非完整年度。
A5: 涵蓋範圍 | B5: ★ 做年度比較時，2026 年不可與 2024、2025 直接相比，請改用同期（1-9 月）比較或看月度彙總的年增率。
A6: 結構規範 | B6: 每張資料工作表第 1 列為欄位標題，第 2 列起為資料，無空列、無小計或合計列。
A7: 結構規範 | B7: 全檔無合併儲存格、無標題橫幅，可直接以 pandas.read_excel(header=0) 讀取。
A8: 結構規範 | B8: 每張資料工作表皆已定義為 Excel 表格物件，名稱為 tbl_ 開頭，可供 BI 工具直接指定資料來源。
A9: 結構規範 | B9: 事實表皆依 年 → 月 → 門市 排序，同一期間為連續區塊，方便切片。
A10: 多期設計 | B10: ★ 租金、座位數、正職編制會逐年調整，放在「門市年度設定」而非門市主檔；明細表以 年+門市 查表帶入。
A11: 多期設計 | B11: ★ 菜單售價逐年調漲，放在「品項年度售價」；品項月銷售以 年+品項 查表帶入當年售價，不可用單一售價回推歷史。
A12: 多期設計 | B12: ★ 門市會開幕與結束營業，事實表為非平衡面板，只有實際營業的月份才有資料列，缺列代表當時未營業。
... A35: 圖表 | B35: 「圖表預覽」工作表僅供人工檢視，不含任何原始資料，自動化流程可略過該表。

Sheet 欄位定義
A1: 工作表 | B1: 欄位位置 | C1: 欄位代碼 | D1: 中文欄名 | E1: 資料型別 | F1: 單位 | G1: 資料來源
A2: 年度參數 | B2: A | C2: year | D2: 年度 | E2: 整數 | F2: 年 | G2: 手動輸入
A3: 年度參數 | B3: B | C3: delivery_fee_rate | D3: 外送平台抽成率 | E3: 百分比 | F3: 小數 | G3: 手動輸入
A4: 年度參數 | B4: C | C4: target_food_rate | D4: 食材成本目標率 | E4: 百分比 | F4: 小數 | G4: 手動輸入
A5: 年度參數 | B5: D | C5: target_labor_rate | D5: 人事成本目標率 | E5: 百分比 | F5: 小數 | G5: 手動輸入
A6: 年度參數 | B6: E | C6: tax_rate | D6: 營業稅率 | E6: 百分比 | F6: 小數 | G6: 手動輸入
A7: 年度參數 | B7: F | C7: target_growth | D7: 年度營收成長目標 | E7: 百分比 | F7: 小數 | G7: 手動輸入
A8: 月曆參數 | B8: A | C8: period | D8: 年月 | E8: 文字 | F8: YYYY-MM | G8: 公式
A9: 月曆參數 | B9: B | C9: year | D9: 年 | E9: 整數 | G9: 手動輸入
A10: 月曆參數 | B10: C | C10: month | D10: 月 | E10: 整數 | F10: 1-12 | G10: 手動輸入
A11: 月曆參數 | B11: D | C11: month_start | D11: 月初日期 | E11: 日期 | G11: 公式
A12: 月曆參數 | B12: E | C12: days | D12: 當月天數 | E12: 整數 | F12: 天 | G12: 公式
A13: 月曆參數 | B13: F | C13: quarter | D13: 季別 | E13: 文字 | F13: Q1-Q4 | G13: 公式
A14: 月曆參數 | B14: G | C14: is_cny | D14: 是否春節月 | E14: 整數 | F14: 1=是 | G14: 手動輸入
A15: 門市主檔 | B15: A | C15: store_id | D15: 門市代號 | E15: 文字 | G15: 手動輸入
A16: 門市主檔 | B16: B | C16: store_name | D16: 門市名稱 | E16: 文字 | G16: 手動輸入
A17: 門市主檔 | B17: C | C17: region | D17: 區域 | E17: 文字 | G17: 手動輸入
A18: 門市主檔 | B18: D | C18: city | D18: 縣市 | E18: 文字 | G18: 手動輸入
A19: 門市主檔 | B19: E | C19: store_type | D19: 店型 | E19: 文字 | G19: 手動輸入
A20: 門市主檔 | B20: F | C20: trade_area | D20: 商圈類型 | E20: 文字 | G20: 手動輸入
A21: 門市主檔 | B21: G | C21: open_date | D21: 開幕日 | E21: 日期 | G21: 手動輸入
A22: 門市主檔 | B22: H | C22: close_date | D22: 結束營業日 | E22: 日期 | F22: 2099-12-31 表示營業中 | G22: 手動輸入
A23: 門市主檔 | B23: I | C23: status | D23: 營業狀態 | E23: 文字 | G23: 手動輸入
A24: 門市年度設定 | B24: A | C24: year | D24: 年度 | E24: 整數 | F24: 年 | G24: 手動輸入
A25: 門市年度設定 | B25: B | C25: store_id | D25: 門市代號 | E25: 文字 | G25: 手動輸入
A26: 門市年度設定 | B26: C | C26: store_name | D26: 門市名稱 | E26: 文字 | G26: 連結 門市主檔
A27: 門市年度設定 | B27: D | C27: store_type | D27: 店型 | E27: 文字 | G27: 連結 門市主檔
A28: 門市年度設定 | B28: E | C28: seats | D28: 座位數 | E28: 整數 | F28: 個 | G28: 手動輸入
A29: 門市年度設定 | B29: F | C29: monthly_rent | D29: 月租金 | E29: 數值 | F29: NT$ | G29: 手動輸入
A30: 門市年度設定 | B30: G | C30: fulltime_headcount | D30: 正職編制 | E30: 整數 | F30: 人 | G30: 手動輸入
A31: 門市年度設定 | B31: H | C31: open_months | D31: 當年營業月數 | E31: 整數 | F31: 月 | G31: 手動輸入
A32: 通路主檔 | B32: A | C32: channel_id | D32: 通路代號 | E32: 文字 | G32: 手動輸入
A33: 通路主檔 | B33: B | C33: channel_name | D33: 通路名稱 | E33: 文字 | G33: 手動輸入
A34: 通路主檔 | B34: C | C34: channel_type | D34: 通路類型 | E34: 文字 | G34: 手動輸入
A35: 通路主檔 | B35: D | C35: has_fee | D35: 是否平台抽成 | E35: 整數 | F35: 1=是 | G35: 手動輸入
A36: 品項主檔 | B36: A | C36: item_id | D36: 品項代號 | E36: 文字 | G36: 手動輸入
A37: 品項主檔 | B37: B | C37: item_name | D37: 品項名稱 | E37: 文字 | G37: 手動輸入
A38: 品項主檔 | B38: C | C38: category | D38: 品項類別 | E38: 文字 | G38: 手動輸入
A39: 品項年度售價 | B39: A | C39: year | D39: 年度 | E39: 整數 | F39: 年 | G39: 手動輸入
A40: 品項年度售價 | B40: B | C40: item_id | D40: 品項代號 | E40: 文字 | G40: 手動輸入
A41: 品項年度售價 | B41: C | C41: item_name | D41: 品項名稱 | E41: 文字 | G41: 連結 品項主檔
A42: 品項年度售價 | B42: D | C42: price | D42: 售價 | E42: 數值 | F42: NT$ | G42: 手動輸入
A43: 通路月營運 | B43: A | C43: period | D43: 年月 | E43: 文字 | F43: YYYY-MM | G43: 公式
A44: 通路月營運 | B44: B | C44: year | D44: 年 | E44: 整數 | G44: 手動輸入
A45: 通路月營運 | B45: C | C45: month | D45: 月 | E45: 整數 | F45: 1-12 | G45: 手動輸入
A46: 通路月營運 | B46: D | C46: store_id | D46: 門市代號 | E46: 文字 | G46: 手動輸入
A47: 通路月營運 | B47: E | C47: store_name | D47: 門市名稱 | E47: 文字 | G47: 連結 門市主檔
A48: 通路月營運 | B48: F | C48: channel_id | D48: 通路代號 | E48: 文字 | G48: 手動輸入
A49: 通路月營運 | B49: G | C49: channel_name | D49: 通路名稱 | E49: 文字 | G49: 連結 通路主檔
A50: 通路月營運 | B50: H | C50: channel_type | D50: 通路類型 | E50: 文字 | G50: 連結 通路主檔
A51: 通路月營運 | B51: I | C51: revenue | D51: 營業額 | E51: 數值 | F51: NT$ | G51: 手動輸入
A52: 通路月營運 | B52: J | C52: orders | D52: 訂單數 | E52: 整數 | F52: 筆 | G52: 手動輸入
A53: 通路月營運 | B53: K | C53: guests | D53: 來客數 | E53: 整數 | F53: 人次 | G53: 手動輸入
A54: 通路月營運 | B54: L | C54: avg_order_value | D54: 平均訂單金額 | E54: 數值 | F54: NT$ | G54: 公式
A55: 通路月營運 | B55: M | C55: fee_rate | D55: 平台抽成率 | E55: 百分比 | F55: 小數 | G55: 公式
A56: 通路月營運 | B56: N | C56: fee_amount | D56: 平台抽成金額 | E56: 數值 | F56: NT$ | G56: 公式
A57: 通路月營運 | B57: O | C57: net_revenue | D57: 扣除抽成後淨收入 | E57: 數值 | F57: NT$ | G57: 公式
A58: 月營運明細 | B58: A | C58: period | D58: 年月 | E58: 文字 | F58: YYYY-MM | G58: 公式
A59: 月營運明細 | B59: B | C59: year | D59: 年 | E59: 整數 | G59: 手動輸入
A60: 月營運明細 | B60: C | C60: month | D60: 月 | E60: 整數 | F60: 1-12 | G60: 手動輸入
A61: 月營運明細 | B61: D | C61: store_id | D61: 門市代號 | E61: 文字 | G61: 手動輸入
A62: 月營運明細 | B62: E | C62: store_name | D62: 門市名稱 | E62: 文字 | G62: 連結 門市主檔
A63: 月營運明細 | B63: F | C63: region | D63: 區域 | E63: 文字 | G63: 連結 門市主檔
A64: 月營運明細 | B64: G | C64: store_type | D64: 店型 | E64: 文字 | G64: 連結 門市主檔
A65: 月營運明細 | B65: H | C65: open_days | D65: 當月營業天數 | E65: 整數 | F65: 天 | G65: 手動輸入
A66: 月營運明細 | B66: I | C66: seats | D66: 座位數 | E66: 整數 | F66: 個 | G66: 連結 門市年度設定
A67: 月營運明細 | B67: J | C67: revenue | D67: 營業額 | E67: 數值 | F67: NT$ | G67: 彙總 通路月營運
A68: 月營運明細 | B68: K | C68: guests | D68: 來客數 | E68: 整數 | F68: 人次 | G68: 彙總 通路月營運
A69: 月營運明細 | B69: L | C69: cost_food | D69: 食材成本 | E69: 數值 | F69: NT$ | G69: 手動輸入
A70: 月營運明細 | B70: M | C70: cost_labor | D70: 人事成本 | E70: 數值 | F70: NT$ | G70: 手動輸入
A71: 月營運明細 | B71: N | C71: cost_rent | D71: 租金 | E71: 數值 | F71: NT$ | G71: 連結 門市年度設定
A72: 月營運明細 | B72: O | C72: cost_utility | D72: 水電及雜支 | E72: 數值 | F72: NT$ | G72: 手動輸入
A73: 月營運明細 | B73: P | C73: cost_mkt | D73: 行銷費用 | E73: 數值 | F73: NT$ | G73: 手動輸入
A74: 月營運明細 | B74: Q | C74: cost_fee | D74: 外送平台抽成 | E74: 數值 | F74: NT$ | G74: 彙總 通路月營運
A75: 月營運明細 | B75: R | C75: cost_total | D75: 總成本 | E75: 數值 | F75: NT$ | G75: 公式
A76: 月營運明細 | B76: S | C76: op_profit | D76: 營業利益 | E76: 數值 | F76: NT$ | G76: 公式
... A84: 品項月銷售 | B84: A | C84: period | D84: 年月 | E84: 文字 | F84: YYYY-MM | G84: 公式
A85: 品項月銷售 | B85: B | C85: year | D85: 年 | E85: 整數 | G85: 手動輸入
A86: 品項月銷售 | B86: C | C86: month | D86: 月 | E86: 整數 | F86: 1-12 | G86: 手動輸入
A87: 品項月銷售 | B87: D | C87: store_id | D87: 門市代號 | E87: 文字 | G87: 手動輸入
A88: 品項月銷售 | B88: E | C88: item_id | D88: 品項代號 | E88: 文字 | G88: 手動輸入
A89: 品項月銷售 | B89: F | C89: item_name | D89: 品項名稱 | E89: 文字 | G89: 連結 品項主檔
A90: 品項月銷售 | B90: G | C90: category | D90: 品項類別 | E90: 文字 | G90: 連結 品項主檔
A91: 品項月銷售 | B91: H | C91: price | D91: 當年售價 | E91: 數值 | F91: NT$ | G91: 連結 品項年度售價
A92: 品項月銷售 | B92: I | C92: qty | D92: 銷售份數 | E92: 整數 | F92: 份 | G92: 手動輸入
A93: 品項月銷售 | B93: J | C93: amount | D93: 銷售金額 | E93: 數值 | F93: NT$ | G93: 公式
A94: 門市年度彙總 | B94: A | C94: year | D94: 年度 | E94: 整數 | F94: 年 | G94: 手動輸入
A95: 門市年度彙總 | B95: B | C95: store_id | D95: 門市代號 | E95: 文字 | G95: 手動輸入
A96: 門市年度彙總 | B96: C | C96: store_name | D96: 門市名稱 | E96: 文字 | G96: 連結 門市主檔
A97: 門市年度彙總 | B97: D | C97: region | D97: 區域 | E97: 文字 | G97: 連結 門市主檔
A98: 門市年度彙總 | B98: E | C98: store_type | D98: 店型 | E98: 文字 | G98: 連結 門市主檔
A99: 門市年度彙總 | B99: F | C99: open_months | D99: 營業月數 | E99: 整數 | F99: 月 | G99: 公式
A100: 門市年度彙總 | B100: G | C100: open_days | D100: 營業天數 | E100: 整數 | F100: 天 | G100: 公式
A101: 門市年度彙總 | B101: H | C101: revenue | D101: 營業額 | E101: 數值 | F101: NT$ | G101: 公式
A102: 門市年度彙總 | B102: I | C102: cost_total | D102: 總成本 | E102: 數值 | F102: NT$ | G102: 公式
A103: 門市年度彙總 | B103: J | C103: op_profit | D103: 營業利益 | E103: 數值 | F103: NT$ | G103: 公式
A104: 門市年度彙總 | B104: K | C104: op_margin | D104: 營業利益率 | E104: 百分比 | F104: 小數 | G104: 公式
A105: 門市年度彙總 | B105: L | C105: guests | D105: 來客數 | E105: 整數 | F105: 人次 | G105: 公式
A106: 門市年度彙總 | B106: M | C106: avg_ticket | D106: 平均客單價 | E106: 數值 | F106: NT$ | G106: 公式
A107: 門市年度彙總 | B107: N | C107: rev_per_day | D107: 日均營業額 | E107: 數值 | F107: NT$ | G107: 公式
...

Sheet 年度參數
A1: 年度 | B1: 外送平台抽成率 | C1: 食材成本目標率 | D1: 人事成本目標率 | E1: 營業稅率 | F1: 年度營收成長目標
A2: 2024 | B2: 0.33 | C2: 0.32 | D2: 0.255 | E2: 0.05 | F2: 0.08
A3: 2025 | B3: 0.34 | C3: 0.315 | D3: 0.262 | E3: 0.05 | F3: 0.07
A4: 2026 | B4: 0.345 | C4: 0.318 | D4: 0.27 | E4: 0.05 | F4: 0.06

Sheet 月曆參數
A1: 年月 | B1: 年 | C1: 月 | D1: 月初日期 | E1: 當月天數 | F1: 季別 | G1: 是否春節月
A2: =TEXT(B2,"0")&"-"&TEXT(C2,"00") -> 2024-01 | B2: 2024 | C2: 1 | D2: =DATE(B2,C2,1) -> 45292 | E2: =DAY(EOMONTH(D2,0)) -> 31 | F2: ="Q"&ROUNDUP(C2/3,0) -> Q1 | G2: 1
A3: =TEXT(B3,"0")&"-"&TEXT(C3,"00") -> 2024-02 | B3: 2024 | C3: 2 | D3: =DATE(B3,C3,1) -> 45323 | E3: =DAY(EOMONTH(D3,0)) -> 29 | F3: ="Q"&ROUNDUP(C3/3,0) -> Q1 | G3: 1
A4: =TEXT(B4,"0")&"-"&TEXT(C4,"00") -> 2024-03 | B4: 2024 | C4: 3 | D4: =DATE(B4,C4,1) -> 45352 | E4: =DAY(EOMONTH(D4,0)) -> 31 | F4: ="Q"&ROUNDUP(C4/3,0) -> Q1 | G4: 0
A5: =TEXT(B5,"0")&"-"&TEXT(C5,"00") -> 2024-04 | B5: 2024 | C5: 4 | D5: =DATE(B5,C5,1) -> 45383 | E5: =DAY(EOMONTH(D5,0)) -> 30 | F5: ="Q"&ROUNDUP(C5/3,0) -> Q2 | G5: 0
A6: =TEXT(B6,"0")&"-"&TEXT(C6,"00") -> 2024-05 | B6: 2024 | C6: 5 | D6: =DATE(B6,C6,1) -> 45413 | E6: =DAY(EOMONTH(D6,0)) -> 31 | F6: ="Q"&ROUNDUP(C6/3,0) -> Q2 | G6: 0
A7: =TEXT(B7,"0")&"-"&TEXT(C7,"00") -> 2024-06 | B7: 2024 | C7: 6 | D7: =DATE(B7,C7,1) -> 45444 | E7: =DAY(EOMONTH(D7,0)) -> 30 | F7: ="Q"&ROUNDUP(C7/3,0) -> Q2 | G7: 0
A8: =TEXT(B8,"0")&"-"&TEXT(C8,"00") -> 2024-07 | B8: 2024 | C8: 7 | D8: =DATE(B8,C8,1) -> 45474 | E8: =DAY(EOMONTH(D8,0)) -> 31 | F8: ="Q"&ROUNDUP(C8/3,0) -> Q3 | G8: 0
A9: =TEXT(B9,"0")&"-"&TEXT(C9,"00") -> 2024-08 | B9: 2024 | C9: 8 | D9: =DATE(B9,C9,1) -> 45505 | E9: =DAY(EOMONTH(D9,0)) -> 31 | F9: ="Q"&ROUNDUP(C9/3,0) -> Q3 | G9: 0
A10: =TEXT(B10,"0")&"-"&TEXT(C10,"00") -> 2024-09 | B10: 2024 | C10: 9 | D10: =DATE(B10,C10,1) -> 45536 | E10: =DAY(EOMONTH(D10,0)) -> 30 | F10: ="Q"&ROUNDUP(C10/3,0) -> Q3 | G10: 0
A11: =TEXT(B11,"0")&"-"&TEXT(C11,"00") -> 2024-10 | B11: 2024 | C11: 10 | D11: =DATE(B11,C11,1) -> 45566 | E11: =DAY(EOMONTH(D11,0)) -> 31 | F11: ="Q"&ROUNDUP(C11/3,0) -> Q4 | G11: 0
A12: =TEXT(B12,"0")&"-"&TEXT(C12,"00") -> 2024-11 | B12: 2024 | C12: 11 | D12: =DATE(B12,C12,1) -> 45597 | E12: =DAY(EOMONTH(D12,0)) -> 30 | F12: ="Q"&ROUNDUP(C12/3,0) -> Q4 | G12: 0
A13: =TEXT(B13,"0")&"-"&TEXT(C13,"00") -> 2024-12 | B13: 2024 | C13: 12 | D13: =DATE(B13,C13,1) -> 45627 | E13: =DAY(EOMONTH(D13,0)) -> 31 | F13: ="Q"&ROUNDUP(C13/3,0) -> Q4 | G13: 0
... A34: =TEXT(B34,"0")&"-"&TEXT(C34,"00") -> 2026-09 | B34: 2026 | C34: 9 | D34: =DATE(B34,C34,1) -> 46266 | E34: =DAY(EOMONTH(D34,0)) -> 30 | F34: ="Q"&ROUNDUP(C34/3,0) -> Q3 | G34: 0

Sheet 門市主檔
A1: 門市代號 | B1: 門市名稱 | C1: 區域 | D1: 縣市 | E1: 店型 | F1: 商圈類型 | G1: 開幕日 | H1: 結束營業日 | I1: 營業狀態
A2: TP01 | B2: 台北信義旗艦店 | C2: 北區 | D2: 台北市 | E2: 旗艦店 | F2: 百貨商圈 | G2: 43539 | H2: 73050 | I2: 營業中
A3: TP02 | B3: 台北中山店 | C3: 北區 | D3: 台北市 | E3: 標準店 | F3: 辦公商圈 | G3: 44013 | H3: 73050 | I3: 營業中
A4: TP03 | B4: 台北東門店 | C4: 北區 | D4: 台北市 | E4: 小型店 | F4: 住宅商圈 | G4: 44445 | H4: 73050 | I4: 營業中
A5: TP04 | B5: 台北松江店 | C5: 北區 | D5: 台北市 | E5: 外帶專門店 | F5: 辦公商圈 | G5: 45064 | H5: 73050 | I5: 營業中
A6: NT01 | B6: 新北板橋店 | C6: 北區 | D6: 新北市 | E6: 標準店 | F6: 百貨商圈 | G6: 44336 | H6: 73050 | I6: 營業中
A7: NT02 | B7: 新北新莊店 | C7: 北區 | D7: 新北市 | E7: 標準店 | F7: 住宅商圈 | G7: 44631 | H7: 73050 | I7: 營業中
A8: NT03 | B8: 新北三重店 | C8: 北區 | D8: 新北市 | E8: 小型店 | F8: 住宅商圈 | G8: 45140 | H8: 45900 | I8: 已結束
A9: TY01 | B9: 桃園中壢店 | C9: 北區 | D9: 桃園市 | E9: 標準店 | F9: 車站商圈 | G9: 44814 | H9: 73050 | I9: 營業中
A10: TY02 | B10: 桃園藝文店 | C10: 北區 | D10: 桃園市 | E10: 標準店 | F10: 住宅商圈 | G10: 45394 | H10: 73050 | I10: 營業中
A11: HC01 | B11: 新竹巨城店 | C11: 北區 | D11: 新竹市 | E11: 旗艦店 | F11: 百貨商圈 | G11: 44525 | H11: 73050 | I11: 營業中
A12: HC02 | B12: 新竹竹北店 | C12: 北區 | D12: 新竹縣 | E12: 標準店 | F12: 住宅商圈 | G12: 45842 | H12: 73050 | I12: 營業中
A13: TC01 | B13: 台中逢甲店 | C13: 中區 | D13: 台中市 | E13: 標準店 | F13: 夜市商圈 | G13: 44143 | H13: 73050 | I13: 營業中
... A25: HL01 | B25: 花蓮中正店 | C25: 東區 | D25: 花蓮縣 | E25: 標準店 | F25: 觀光商圈 | G25: 46174 | H25: 73050 | I25: 營業中

Sheet 門市年度設定
A1: 年度 | B1: 門市代號 | C1: 門市名稱 | D1: 店型 | E1: 座位數 | F1: 月租金 | G1: 正職編制 | H1: 當年營業月數
A2: 2024 | B2: CH01 | C2: =INDEX(門市主檔!$B$2:$B$25,MATCH($B2,門市主檔!$A$2:$A$25,0)) -> 彰化員林店 | D2: =INDEX(門市主檔!$E$2:$E$25,MATCH($B2,門市主檔!$A$2:$A$25,0)) -> 小型店 | E2: 54 | F2: 83000 | G2: 11 | H2: 11
A3: 2024 | B3: HC01 | C3: =INDEX(門市主檔!$B$2:$B$25,MATCH($B3,門市主檔!$A$2:$A$25,0)) -> 新竹巨城店 | D3: =INDEX(門市主檔!$E$2:$E$25,MATCH($B3,門市主檔!$A$2:$A$25,0)) -> 旗艦店 | E3: 118 | F3: 512000 | G3: 16 | H3: 12
A4: 2024 | B4: KH01 | C4: =INDEX(門市主檔!$B$2:$B$25,MATCH($B4,門市主檔!$A$2:$A$25,0)) -> 高雄左營店 | D4: =INDEX(門市主檔!$E$2:$E$25,MATCH($B4,門市主檔!$A$2:$A$25,0)) -> 旗艦店 | E4: 119 | F4: 464000 | G4: 15 | H4: 12
A5: 2024 | B5: KH02 | C5: =INDEX(門市主檔!$B$2:$B$25,MATCH($B5,門市主檔!$A$2:$A$25,0)) -> 高雄三多店 | D5: =INDEX(門市主檔!$E$2:$E$25,MATCH($B5,門市主檔!$A$2:$A$25,0)) -> 標準店 | E5: 77 | F5: 204000 | G5: 12 | H5: 12
A6: 2024 | B6: NT01 | C6: =INDEX(門市主檔!$B$2:$B$25,MATCH($B6,門市主檔!$A$2:$A$25,0)) -> 新北板橋店 | D6: =INDEX(門市主檔!$E$2:$E$25,MATCH($B6,門市主檔!$A$2:$A$25,0)) -> 標準店 | E6: 92 | F6: 282000 | G6: 12 | H6: 12
A7: 2024 | B7: NT02 | C7: =INDEX(門市主檔!$B$2:$B$25,MATCH($B7,門市主檔!$A$2:$A$25,0)) -> 新北新莊店 | D7: =INDEX(門市主檔!$E$2:$E$25,MATCH($B7,門市主檔!$A$2:$A$25,0)) -> 標準店 | E7: 76 | F7: 239000 | G7: 12 | H7: 12
A8: 2024 | B8: NT03 | C8: =INDEX(門市主檔!$B$2:$B$25,MATCH($B8,門市主檔!$A$2:$A$25,0)) -> 新北三重店 | D8: =INDEX(門市主檔!$E$2:$E$25,MATCH($B8,門市主檔!$A$2:$A$25,0)) -> 小型店 | E8: 50 | F8: 113000 | G8: 9 | H8: 12
A9: 2024 | B9: TC01 | C9: =INDEX(門市主檔!$B$2:$B$25,MATCH($B9,門市主檔!$A$2:$A$25,0)) -> 台中逢甲店 | D9: =INDEX(門市主檔!$E$2:$E$25,MATCH($B9,門市主檔!$A$2:$A$25,0)) -> 標準店 | E9: 83 | F9: 316000 | G9: 11 | H9: 12
A10: 2024 | B10: TC02 | C10: =INDEX(門市主檔!$B$2:$B$25,MATCH($B10,門市主檔!$A$2:$A$25,0)) -> 台中七期店 | D10: =INDEX(門市主檔!$E$2:$E$25,MATCH($B10,門市主檔!$A$2:$A$25,0)) -> 旗艦店 | E10: 124 | F10: 474000 | G10: 18 | H10: 12
A11: 2024 | B11: TC03 | C11: =INDEX(門市主檔!$B$2:$B$25,MATCH($B11,門市主檔!$A$2:$A$25,0)) -> 台中一中店 | D11: =INDEX(門市主檔!$E$2:$E$25,MATCH($B11,門市主檔!$A$2:$A$25,0)) -> 小型店 | E11: 52 | F11: 102000 | G11: 7 | H11: 12
A12: 2024 | B12: TN01 | C12: =INDEX(門市主檔!$B$2:$B$25,MATCH($B12,門市主檔!$A$2:$A$25,0)) -> 台南中西店 | D12: =INDEX(門市主檔!$E$2:$E$25,MATCH($B12,門市主檔!$A$2:$A$25,0)) -> 標準店 | E12: 76 | F12: 205000 | G12: 10 | H12: 12
A13: 2024 | B13: TN02 | C13: =INDEX(門市主檔!$B$2:$B$25,MATCH($B13,門市主檔!$A$2:$A$25,0)) -> 台南東寧店 | D13: =INDEX(門市主檔!$E$2:$E$25,MATCH($B13,門市主檔!$A$2:$A$25,0)) -> 小型店 | E13: 51 | F13: 91000 | G13: 8 | H13: 12
... A63: 2026 | B63: YL01 | C63: =INDEX(門市主檔!$B$2:$B$25,MATCH($B63,門市主檔!$A$2:$A$25,0)) -> 雲林斗六店 | D63: =INDEX(門市主檔!$E$2:$E$25,MATCH($B63,門市主檔!$A$2:$A$25,0)) -> 標準店 | E63: 90 | F63: 170000 | G63: 12 | H63: 9

Sheet 通路主檔
A1: 通路代號 | B1: 通路名稱 | C1: 通路類型 | D1: 是否平台抽成
A2: CH1 | B2: 內用 | C2: 店內 | D2: 0
A3: CH2 | B3: 外帶 | C3: 店內 | D3: 0
A4: CH3 | B4: 外送平台 A | C4: 外送平台 | D4: 1
A5: CH4 | B5: 外送平台 B | C5: 外送平台 | D5: 1

Sheet 品項主檔
A1: 品項代號 | B1: 品項名稱 | C1: 品項類別
A2: MI01 | B2: 招牌牛肉麵 | C2: 主食
A3: MI02 | B3: 三杯雞定食 | C3: 主食
A4: MI03 | B4: 蔥油雞腿飯 | C4: 主食
A5: MI04 | B5: 黑胡椒豬排飯 | C5: 主食
A6: MI05 | B6: 麻油雞湯麵 | C6: 主食
A7: MI06 | B7: 塔香涼麵 | C7: 主食
A8: MI07 | B8: 海鮮炒飯 | C8: 主食
A9: MI08 | B9: 酸辣湯 | C9: 湯品
A10: MI09 | B10: 招牌滷味拼盤 | C10: 小菜
A11: MI10 | B11: 古早味紅茶 | C11: 飲品

Sheet 品項年度售價
A1: 年度 | B1: 品項代號 | C1: 品項名稱 | D1: 售價
A2: 2024 | B2: MI01 | C2: =INDEX(品項主檔!$B$2:$B$11,MATCH($B2,品項主檔!$A$2:$A$11,0)) -> 招牌牛肉麵 | D2: 280
A3: 2024 | B3: MI02 | C3: =INDEX(品項主檔!$B$2:$B$11,MATCH($B3,品項主檔!$A$2:$A$11,0)) -> 三杯雞定食 | D3: 260
A4: 2024 | B4: MI03 | C4: =INDEX(品項主檔!$B$2:$B$11,MATCH($B4,品項主檔!$A$2:$A$11,0)) -> 蔥油雞腿飯 | D4: 220
A5: 2024 | B5: MI04 | C5: =INDEX(品項主檔!$B$2:$B$11,MATCH($B5,品項主檔!$A$2:$A$11,0)) -> 黑胡椒豬排飯 | D5: 230
A6: 2024 | B6: MI05 | C6: =INDEX(品項主檔!$B$2:$B$11,MATCH($B6,品項主檔!$A$2:$A$11,0)) -> 麻油雞湯麵 | D6: 290
A7: 2024 | B7: MI06 | C7: =INDEX(品項主檔!$B$2:$B$11,MATCH($B7,品項主檔!$A$2:$A$11,0)) -> 塔香涼麵 | D7: 180
A8: 2024 | B8: MI07 | C8: =INDEX(品項主檔!$B$2:$B$11,MATCH($B8,品項主檔!$A$2:$A$11,0)) -> 海鮮炒飯 | D8: 250
A9: 2024 | B9: MI08 | C9: =INDEX(品項主檔!$B$2:$B$11,MATCH($B9,品項主檔!$A$2:$A$11,0)) -> 酸辣湯 | D9: 60
A10: 2024 | B10: MI09 | C10: =INDEX(品項主檔!$B$2:$B$11,MATCH($B10,品項主檔!$A$2:$A$11,0)) -> 招牌滷味拼盤 | D10: 120
A11: 2024 | B11: MI10 | C11: =INDEX(品項主檔!$B$2:$B$11,MATCH($B11,品項主檔!$A$2:$A$11,0)) -> 古早味紅茶 | D11: 45
A12: 2025 | B12: MI01 | C12: =INDEX(品項主檔!$B$2:$B$11,MATCH($B12,品項主檔!$A$2:$A$11,0)) -> 招牌牛肉麵 | D12: 295
A13: 2025 | B13: MI02 | C13: =INDEX(品項主檔!$B$2:$B$11,MATCH($B13,品項主檔!$A$2:$A$11,0)) -> 三杯雞定食 | D13: 260
... A31: 2026 | B31: MI10 | C31: =INDEX(品項主檔!$B$2:$B$11,MATCH($B31,品項主檔!$A$2:$A$11,0)) -> 古早味紅茶 | D31: 45

Sheet 通路月營運
A1: 年月 | B1: 年 | C1: 月 | D1: 門市代號 | E1: 門市名稱 | F1: 通路代號 | G1: 通路名稱 | H1: 通路類型 | I1: 營業額 | J1: 訂單數 | K1: 來客數 | L1: 平均訂單金額 | M1: 平台抽成率 | N1: 平台抽成金額 | O1: 扣除抽成後淨收入
A2: =TEXT(B2,"0")&"-"&TEXT(C2,"00") -> 2024-01 | B2: 2024 | C2: 1 | D2: CH01 | E2: =INDEX(門市主檔!$B$2:$B$25,MATCH($D2,門市主檔!$A$2:$A$25,0)) -> 彰化員林店 | F2: CH1 | G2: =INDEX(通路主檔!$B$2:$B$5,MATCH($F2,通路主檔!$A$2:$A$5,0)) -> 內用 | H2: =INDEX(通路主檔!$C$2:$C$5,MATCH($F2,通路主檔!$A$2:$A$5,0)) -> 店內 | I2: 265300 | J2: 326 | K2: 753 | L2: =IF(J2=0,0,I2/J2) -> 813.80368 | M2: =INDEX(通路主檔!$D$2:$D$5,MATCH($F2,通路主檔!$A$2:$A$5,0))*INDEX(年度參數!$B$2:$B$4,MATCH($B2,年度參數!$A$2:$A$4,0)) -> 0 | N2: =I2*M2 -> 0 | O2: =I2-N2 -> 265300
A3: =TEXT(B3,"0")&"-"&TEXT(C3,"00") -> 2024-01 | B3: 2024 | C3: 1 | D3: CH01 | E3: =INDEX(門市主檔!$B$2:$B$25,MATCH($D3,門市主檔!$A$2:$A$25,0)) -> 彰化員林店 | F3: CH2 | G3: =INDEX(通路主檔!$B$2:$B$5,MATCH($F3,通路主檔!$A$2:$A$5,0)) -> 外帶 | H3: =INDEX(通路主檔!$C$2:$C$5,MATCH($F3,通路主檔!$A$2:$A$5,0)) -> 店內 | I3: 235500 | J3: 775 | K3: 1067 | L3: =IF(J3=0,0,I3/J3) -> 303.87097 | M3: =INDEX(通路主檔!$D$2:$D$5,MATCH($F3,通路主檔!$A$2:$A$5,0))*INDEX(年度參數!$B$2:$B$4,MATCH($B3,年度參數!$A$2:$A$4,0)) -> 0 | N3: =I3*M3 -> 0 | O3: =I3-N3 -> 235500
A4: =TEXT(B4,"0")&"-"&TEXT(C4,"00") -> 2024-01 | B4: 2024 | C4: 1 | D4: CH01 | E4: =INDEX(門市主檔!$B$2:$B$25,MATCH($D4,門市主檔!$A$2:$A$25,0)) -> 彰化員林店 | F4: CH3 | G4: =INDEX(通路主檔!$B$2:$B$5,MATCH($F4,通路主檔!$A$2:$A$5,0)) -> 外送平台 A | H4: =INDEX(通路主檔!$C$2:$C$5,MATCH($F4,通路主檔!$A$2:$A$5,0)) -> 外送平台 | I4: 203600 | J4: 361 | K4: 699 | L4: =IF(J4=0,0,I4/J4) -> 563.98892 | M4: =INDEX(通路主檔!$D$2:$D$5,MATCH($F4,通路主檔!$A$2:$A$5,0))*INDEX(年度參數!$B$2:$B$4,MATCH($B4,年度參數!$A$2:$A$4,0)) -> 0.33 | N4: =I4*M4 -> 67188 | O4: =I4-N4 -> 136412
A5: =TEXT(B5,"0")&"-"&TEXT(C5,"00") -> 2024-01 | B5: 2024 | C5: 1 | D5: CH01 | E5: =INDEX(門市主檔!$B$2:$B$25,MATCH($D5,門市主檔!$A$2:$A$25,0)) -> 彰化員林店 | F5: CH4 | G5: =INDEX(通路主檔!$B$2:$B$5,MATCH($F5,通路主檔!$A$2:$A$5,0)) -> 外送平台 B | H5: =INDEX(通路主檔!$C$2:$C$5,MATCH($F5,通路主檔!$A$2:$A$5,0)) -> 外送平台 | I5: 132500 | J5: 260 | K5: 490 | L5: =IF(J5=0,0,I5/J5) -> 509.61538 | M5: =INDEX(通路主檔!$D$2:$D$5,MATCH($F5,通路主檔!$A$2:$A$5,0))*INDEX(年度參數!$B$2:$B$4,MATCH($B5,年度參數!$A$2:$A$4,0)) -> 0.33 | N5: =I5*M5 -> 43725 | O5: =I5-N5 -> 88775
A6: =TEXT(B6,"0")&"-"&TEXT(C6,"00") -> 2024-01 | B6: 2024 | C6: 1 | D6: HC01 | E6: =INDEX(門市主檔!$B$2:$B$25,MATCH($D6,門市主檔!$A$2:$A$25,0)) -> 新竹巨城店 | F6: CH1 | G6: =INDEX(通路主檔!$B$2:$B$5,MATCH($F6,通路主檔!$A$2:$A$5,0)) -> 內用 | H6: =INDEX(通路主檔!$C$2:$C$5,MATCH($F6,通路主檔!$A$2:$A$5,0)) -> 店內 | I6: 1098300 | J6: 1438 | K6: 3272 | L6: =IF(J6=0,0,I6/J6) -> 763.76912 | M6: =INDEX(通路主檔!$D$2:$D$5,MATCH($F6,通路主檔!$A$2:$A$5,0))*INDEX(年度參數!$B$2:$B$4,MATCH($B6,年度參數!$A$2:$A$4,0)) -> 0 | N6: =I6*M6 -> 0 | O6: =I6-N6 -> 1098300
A7: =TEXT(B7,"0")&"-"&TEXT(C7,"00") -> 2024-01 | B7: 2024 | C7: 1 | D7: HC01 | E7: =INDEX(門市主檔!$B$2:$B$25,MATCH($D7,門市主檔!$A$2:$A$25,0)) -> 新竹巨城店 | F7: CH2 | G7: =INDEX(通路主檔!$B$2:$B$5,MATCH($F7,通路主檔!$A$2:$A$5,0)) -> 外帶 | H7: =INDEX(通路主檔!$C$2:$C$5,MATCH($F7,通路主檔!$A$2:$A$5,0)) -> 店內 | I7: 361300 | J7: 1106 | K7: 1333 | L7: =IF(J7=0,0,I7/J7) -> 326.67269 | M7: =INDEX(通路主檔!$D$2:$D$5,MATCH($F7,通路主檔!$A$2:$A$5,0))*INDEX(年度參數!$B$2:$B$4,MATCH($B7,年度參數!$A$2:$A$4,0)) -> 0 | N7: =I7*M7 -> 0 | O7: =I7-N7 -> 361300
A8: =TEXT(B8,"0")&"-"&TEXT(C8,"00") -> 2024-01 | B8: 2024 | C8: 1 | D8: HC01 | E8: =INDEX(門市主檔!$B$2:$B$25,MATCH($D8,門市主檔!$A$2:$A$25,0)) -> 新竹巨城店 | F8: CH3 | G8: =INDEX(通路主檔!$B$2:$B$5,MATCH($F8,通路主檔!$A$2:$A$5,0)) -> 外送平台 A | H8: =INDEX(通路主檔!$C$2:$C$5,MATCH($F8,通路主檔!$A$2:$A$5,0)) -> 外送平台 | I8: 318200 | J8: 616 | K8: 1106 | L8: =IF(J8=0,0,I8/J8) -> 516.55844 | M8: =INDEX(通路主檔!$D$2:$D$5,MATCH($F8,通路主檔!$A$2:$A$5,0))*INDEX(年度參數!$B$2:$B$4,MATCH($B8,年度參數!$A$2:$A$4,0)) -> 0.33 | N8: =I8*M8 -> 105006 | O8: =I8-N8 -> 213194
A9: =TEXT(B9,"0")&"-"&TEXT(C9,"00") -> 2024-01 | B9: 2024 | C9: 1 | D9: HC01 | E9: =INDEX(門市主檔!$B$2:$B$25,MATCH($D9,門市主檔!$A$2:$A$25,0)) -> 新竹巨城店 | F9: CH4 | G9: =INDEX(通路主檔!$B$2:$B$5,MATCH($F9,通路主檔!$A$2:$A$5,0)) -> 外送平台 B | H9: =INDEX(通路主檔!$C$2:$C$5,MATCH($F9,通路主檔!$A$2:$A$5,0)) -> 外送平台 | I9: 223900 | J9: 430 | K9: 716 | L9: =IF(J9=0,0,I9/J9) -> 520.69767 | M9: =INDEX(通路主檔!$D$2:$D$5,MATCH($F9,通路主檔!$A$2:$A$5,0))*INDEX(年度參數!$B$2:$B$4,MATCH($B9,年度參數!$A$2:$A$4,0)) -> 0.33 | N9: =I9*M9 -> 73887 | O9: =I9-N9 -> 150013
A10: =TEXT(B10,"0")&"-"&TEXT(C10,"00") -> 2024-01 | B10: 2024 | C10: 1 | D10: KH01 | E10: =INDEX(門市主檔!$B$2:$B$25,MATCH($D10,門市主檔!$A$2:$A$25,0)) -> 高雄左營店 | F10: CH1 | G10: =INDEX(通路主檔!$B$2:$B$5,MATCH($F10,通路主檔!$A$2:$A$5,0)) -> 內用 | H10: =INDEX(通路主檔!$C$2:$C$5,MATCH($F10,通路主檔!$A$2:$A$5,0)) -> 店內 | I10: 768000 | J10: 1015 | K10: 2623 | L10: =IF(J10=0,0,I10/J10) -> 756.65025 | M10: =INDEX(通路主檔!$D$2:$D$5,MATCH($F10,通路主檔!$A$2:$A$5,0))*INDEX(年度參數!$B$2:$B$4,MATCH($B10,年度參數!$A$2:$A$4,0)) -> 0 | N10: =I10*M10 -> 0 | O10: =I10-N10 -> 768000
A11: =TEXT(B11,"0")&"-"&TEXT(C11,"00") -> 2024-01 | B11: 2024 | C11: 1 | D11: KH01 | E11: =INDEX(門市主檔!$B$2:$B$25,MATCH($D11,門市主檔!$A$2:$A$25,0)) -> 高雄左營店 | F11: CH2 | G11: =INDEX(通路主檔!$B$2:$B$5,MATCH($F11,通路主檔!$A$2:$A$5,0)) -> 外帶 | H11: =INDEX(通路主檔!$C$2:$C$5,MATCH($F11,通路主檔!$A$2:$A$5,0)) -> 店內 | I11: 278400 | J11: 772 | K11: 1019 | L11: =IF(J11=0,0,I11/J11) -> 360.62176 | M11: =INDEX(通路主檔!$D$2:$D$5,MATCH($F11,通路主檔!$A$2:$A$5,0))*INDEX(年度參數!$B$2:$B$4,MATCH($B11,年度參數!$A$2:$A$4,0)) -> 0 | N11: =I11*M11 -> 0 | O11: =I11-N11 -> 278400
A12: =TEXT(B12,"0")&"-"&TEXT(C12,"00") -> 2024-01 | B12: 2024 | C12: 1 | D12: KH01 | E12: =INDEX(門市主檔!$B$2:$B$25,MATCH($D12,門市主檔!$A$2:$A$25,0)) -> 高雄左營店 | F12: CH3 | G12: =INDEX(通路主檔!$B$2:$B$5,MATCH($F12,通路主檔!$A$2:$A$5,0)) -> 外送平台 A | H12: =INDEX(通路主檔!$C$2:$C$5,MATCH($F12,通路主檔!$A$2:$A$5,0)) -> 外送平台 | I12: 272100 | J12: 559 | K12: 1008 | L12: =IF(J12=0,0,I12/J12) -> 486.76208 | M12: =INDEX(通路主檔!$D$2:$D$5,MATCH($F12,通路主檔!$A$2:$A$5,0))*INDEX(年度參數!$B$2:$B$4,MATCH($B12,年度參數!$A$2:$A$4,0)) -> 0.33 | N12: =I12*M12 -> 89793 | O12: =I12-N12 -> 182307
A13: =TEXT(B13,"0")&"-"&TEXT(C13,"00") -> 2024-01 | B13: 2024 | C13: 1 | D13: KH01 | E13: =INDEX(門市主檔!$B$2:$B$25,MATCH($D13,門市主檔!$A$2:$A$25,0)) -> 高雄左營店 | F13: CH4 | G13: =INDEX(通路主檔!$B$2:$B$5,MATCH($F13,通路主檔!$A$2:$A$5,0)) -> 外送平台 B | H13: =INDEX(通路主檔!$C$2:$C$5,MATCH($F13,通路主檔!$A$2:$A$5,0)) -> 外送平台 | I13: 154900 | J13: 327 | K13: 615 | L13: =IF(J13=0,0,I13/J13) -> 473.70031 | M13: =INDEX(通路主檔!$D$2:$D$5,MATCH($F13,通路主檔!$A$2:$A$5,0))*INDEX(年度參數!$B$2:$B$4,MATCH($B13,年度參數!$A$2:$A$4,0)) -> 0.33 | N13: =I13*M13 -> 51117 | O13: =I13-N13 -> 103783
... A2509: =TEXT(B2509,"0")&"-"&TEXT(C2509,"00") -> 2026-09 | B2509: 2026 | C2509: 9 | D2509: YL01 | E2509: =INDEX(門市主檔!$B$2:$B$25,MATCH($D2509,門市主檔!$A$2:$A$25,0)) -> 雲林斗六店 | F2509: CH4 | G2509: =INDEX(通路主檔!$B$2:$B$5,MATCH($F2509,通路主檔!$A$2:$A$5,0)) -> 外送平台 B | H2509: =INDEX(通路主檔!$C$2:$C$5,MATCH($F2509,通路主檔!$A$2:$A$5,0)) -> 外送平台 | I2509: 209700 | J2509: 421 | K2509: 793 | L2509: =IF(J2509=0,0,I2509/J2509) -> 498.09976 | M2509: =INDEX(通路主檔!$D$2:$D$5,MATCH($F2509,通路主檔!$A$2:$A$5,0))*INDEX(年度參數!$B$2:$B$4,MATCH($B2509,年度參數!$A$2:$A$4,0)) -> 0.345 | N2509: =I2509*M2509 -> 72346.5 | O2509: =I2509-N2509 -> 137353.5

Sheet 月營運明細
A1: 年月 | B1: 年 | C1: 月 | D1: 門市代號 | E1: 門市名稱 | F1: 區域 | G1: 店型 | H1: 當月營業天數 | I1: 座位數 | J1: 營業額 | K1: 來客數 | L1: 食材成本 | M1: 人事成本 | N1: 租金 | O1: 水電及雜支 | P1: 行銷費用 | Q1: 外送平台抽成 | R1: 總成本 | S1: 營業利益 | T1: 營業利益率 | U1: 日均營業額 | V1: 日均來客數 | W1: 平均客單價 | X1: 食材成本率 | Y1: 人事成本率 | Z1: 每座位月營收
A2: =TEXT(B2,"0")&"-"&TEXT(C2,"00") -> 2024-01 | B2: 2024 | C2: 1 | D2: CH01 | E2: =INDEX(門市主檔!$B$2:$B$25,MATCH($D2,門市主檔!$A$2:$A$25,0)) -> 彰化員林店 | F2: =INDEX(門市主檔!$C$2:$C$25,MATCH($D2,門市主檔!$A$2:$A$25,0)) -> 中區 | G2: =INDEX(門市主檔!$E$2:$E$25,MATCH($D2,門市主檔!$A$2:$A$25,0)) -> 小型店 | H2: 31 | I2: =SUMIFS(門市年度設定!$E$2:$E$63,門市年度設定!$A$2:$A$63,$B2,門市年度設定!$B$2:$B$63,$D2) -> 54 | J2: =SUMIFS(通路月營運!$I$2:$I$2509,通路月營運!$B$2:$B$2509,$B2,通路月營運!$C$2:$C$2509,$C2,通路月營運!$D$2:$D$2509,$D2) -> 836900 | K2: =SUMIFS(通路月營運!$K$2:$K$2509,通路月營運!$B$2:$B$2509,$B2,通路月營運!$C$2:$C$2509,$C2,通路月營運!$D$2:$D$2509,$D2) -> 3009 | L2: 282200 | M2: 212800 | N2: =SUMIFS(門市年度設定!$F$2:$F$63,門市年度設定!$A$2:$A$63,$B2,門市年度設定!$B$2:$B$63,$D2) -> 83000 | O2: 38900 | P2: 27400 | Q2: =SUMIFS(通路月營運!$N$2:$N$2509,通路月營運!$B$2:$B$2509,$B2,通路月營運!$C$2:$C$2509,$C2,通路月營運!$D$2:$D$2509,$D2) -> 110913 | R2: =SUM(L2:Q2) -> 755213 | S2: =J2-R2 -> 81687 | T2: =IF(J2=0,0,S2/J2) -> 0.097606644 | U2: =IF(H2=0,0,J2/H2) -> 26996.774 | V2: =IF(H2=0,0,K2/H2) -> 97.064516 | W2: =IF(K2=0,0,J2/K2) -> 278.13227 | X2: =IF(J2=0,0,L2/J2) -> 0.3371968 | Y2: =IF(J2=0,0,M2/J2) -> 0.25427172 | Z2: =IF(I2=0,0,J2/I2) -> 15498.148
A3: =TEXT(B3,"0")&"-"&TEXT(C3,"00") -> 2024-01 | B3: 2024 | C3: 1 | D3: HC01 | E3: =INDEX(門市主檔!$B$2:$B$25,MATCH($D3,門市主檔!$A$2:$A$25,0)) -> 新竹巨城店 | F3: =INDEX(門市主檔!$C$2:$C$25,MATCH($D3,門市主檔!$A$2:$A$25,0)) -> 北區 | G3: =INDEX(門市主檔!$E$2:$E$25,MATCH($D3,門市主檔!$A$2:$A$25,0)) -> 旗艦店 | H3: 31 | I3: =SUMIFS(門市年度設定!$E$2:$E$63,門市年度設定!$A$2:$A$63,$B3,門市年度設定!$B$2:$B$63,$D3) -> 118 | J3: =SUMIFS(通路月營運!$I$2:$I$2509,通路月營運!$B$2:$B$2509,$B3,通路月營運!$C$2:$C$2509,$C3,通路月營運!$D$2:$D$2509,$D3) -> 2001700 | K3: =SUMIFS(通路月營運!$K$2:$K$2509,通路月營運!$B$2:$B$2509,$B3,通路月營運!$C$2:$C$2509,$C3,通路月營運!$D$2:$D$2509,$D3) -> 6427 | L3: 686700 | M3: 520300 | N3: =SUMIFS(門市年度設定!$F$2:$F$63,門市年度設定!$A$2:$A$63,$B3,門市年度設定!$B$2:$B$63,$D3) -> 512000 | O3: 107700 | P3: 45000 | Q3: =SUMIFS(通路月營運!$N$2:$N$2509,通路月營運!$B$2:$B$2509,$B3,通路月營運!$C$2:$C$2509,$C3,通路月營運!$D$2:$D$2509,$D3) -> 178893 | R3: =SUM(L3:Q3) -> 2050593 | S3: =J3-R3 -> -48893 | T3: =IF(J3=0,0,S3/J3) -> -0.024425738 | U3: =IF(H3=0,0,J3/H3) -> 64570.968 | V3: =IF(H3=0,0,K3/H3) -> 207.32258 | W3: =IF(K3=0,0,J3/K3) -> 311.45169 | X3: =IF(J3=0,0,L3/J3) -> 0.3430584 | Y3: =IF(J3=0,0,M3/J3) -> 0.25992906 | Z3: =IF(I3=0,0,J3/I3) -> 16963.559
A4: =TEXT(B4,"0")&"-"&TEXT(C4,"00") -> 2024-01 | B4: 2024 | C4: 1 | D4: KH01 | E4: =INDEX(門市主檔!$B$2:$B$25,MATCH($D4,門市主檔!$A$2:$A$25,0)) -> 高雄左營店 | F4: =INDEX(門市主檔!$C$2:$C$25,MATCH($D4,門市主檔!$A$2:$A$25,0)) -> 南區 | G4: =INDEX(門市主檔!$E$2:$E$25,MATCH($D4,門市主檔!$A$2:$A$25,0)) -> 旗艦店 | H4: 31 | I4: =SUMIFS(門市年度設定!$E$2:$E$63,門市年度設定!$A$2:$A$63,$B4,門市年度設定!$B$2:$B$63,$D4) -> 119 | J4: =SUMIFS(通路月營運!$I$2:$I$2509,通路月營運!$B$2:$B$2509,$B4,通路月營運!$C$2:$C$2509,$C4,通路月營運!$D$2:$D$2509,$D4) -> 1473400 | K4: =SUMIFS(通路月營運!$K$2:$K$2509,通路月營運!$B$2:$B$2509,$B4,通路月營運!$C$2:$C$2509,$C4,通路月營運!$D$2:$D$2509,$D4) -> 5265 | L4: 434900 | M4: 398500 | N4: =SUMIFS(門市年度設定!$F$2:$F$63,門市年度設定!$A$2:$A$63,$B4,門市年度設定!$B$2:$B$63,$D4) -> 464000 | O4: 101600 | P4: 43500 | Q4: =SUMIFS(通路月營運!$N$2:$N$2509,通路月營運!$B$2:$B$2509,$B4,通路月營運!$C$2:$C$2509,$C4,通路月營運!$D$2:$D$2509,$D4) -> 140910 | R4: =SUM(L4:Q4) -> 1583410 | S4: =J4-R4 -> -110010 | T4: =IF(J4=0,0,S4/J4) -> -0.074664042 | U4: =IF(H4=0,0,J4/H4) -> 47529.032 | V4: =IF(H4=0,0,K4/H4) -> 169.83871 | W4: =IF(K4=0,0,J4/K4) -> 279.84805 | X4: =IF(J4=0,0,L4/J4) -> 0.29516764 | Y4: =IF(J4=0,0,M4/J4) -> 0.27046287 | Z4: =IF(I4=0,0,J4/I4) -> 12381.513
A5: =TEXT(B5,"0")&"-"&TEXT(C5,"00") -> 2024-01 | B5: 2024 | C5: 1 | D5: KH02 | E5: =INDEX(門市主檔!$B$2:$B$25,MATCH($D5,門市主檔!$A$2:$A$25,0)) -> 高雄三多店 | F5: =INDEX(門市主檔!$C$2:$C$25,MATCH($D5,門市主檔!$A$2:$A$25,0)) -> 南區 | G5: =INDEX(門市主檔!$E$2:$E$25,MATCH($D5,門市主檔!$A$2:$A$25,0)) -> 標準店 | H5: 27 | I5: =SUMIFS(門市年度設定!$E$2:$E$63,門市年度設定!$A$2:$A$63,$B5,門市年度設定!$B$2:$B$63,$D5) -> 77 | J5: =SUMIFS(通路月營運!$I$2:$I$2509,通路月營運!$B$2:$B$2509,$B5,通路月營運!$C$2:$C$2509,$C5,通路月營運!$D$2:$D$2509,$D5) -> 1155400 | K5: =SUMIFS(通路月營運!$K$2:$K$2509,通路月營運!$B$2:$B$2509,$B5,通路月營運!$C$2:$C$2509,$C5,通路月營運!$D$2:$D$2509,$D5) -> 4036 | L5: 383600 | M5: 285600 | N5: =SUMIFS(門市年度設定!$F$2:$F$63,門市年度設定!$A$2:$A$63,$B5,門市年度設定!$B$2:$B$63,$D5) -> 204000 | O5: 62300 | P5: 34500 | Q5: =SUMIFS(通路月營運!$N$2:$N$2509,通路月營運!$B$2:$B$2509,$B5,通路月營運!$C$2:$C$2509,$C5,通路月營運!$D$2:$D$2509,$D5) -> 123948 | R5: =SUM(L5:Q5) -> 1093948 | S5: =J5-R5 -> 61452 | T5: =IF(J5=0,0,S5/J5) -> 0.053186775 | U5: =IF(H5=0,0,J5/H5) -> 42792.593 | V5: =IF(H5=0,0,K5/H5) -> 149.48148 | W5: =IF(K5=0,0,J5/K5) -> 286.27354 | X5: =IF(J5=0,0,L5/J5) -> 0.33200623 | Y5: =IF(J5=0,0,M5/J5) -> 0.24718712 | Z5: =IF(I5=0,0,J5/I5) -> 15005.195
A6: =TEXT(B6,"0")&"-"&TEXT(C6,"00") -> 2024-01 | B6: 2024 | C6: 1 | D6: NT01 | E6: =INDEX(門市主檔!$B$2:$B$25,MATCH($D6,門市主檔!$A$2:$A$25,0)) -> 新北板橋店 | F6: =INDEX(門市主檔!$C$2:$C$25,MATCH($D6,門市主檔!$A$2:$A$25,0)) -> 北區 | G6: =INDEX(門市主檔!$E$2:$E$25,MATCH($D6,門市主檔!$A$2:$A$25,0)) -> 標準店 | H6: 31 | I6: =SUMIFS(門市年度設定!$E$2:$E$63,門市年度設定!$A$2:$A$63,$B6,門市年度設定!$B$2:$B$63,$D6) -> 92 | J6: =SUMIFS(通路月營運!$I$2:$I$2509,通路月營運!$B$2:$B$2509,$B6,通路月營運!$C$2:$C$2509,$C6,通路月營運!$D$2:$D$2509,$D6) -> 1569900 | K6: =SUMIFS(通路月營運!$K$2:$K$2509,通路月營運!$B$2:$B$2509,$B6,通路月營運!$C$2:$C$2509,$C6,通路月營運!$D$2:$D$2509,$D6) -> 5297 | L6: 527900 | M6: 404200 | N6: =SUMIFS(門市年度設定!$F$2:$F$63,門市年度設定!$A$2:$A$63,$B6,門市年度設定!$B$2:$B$63,$D6) -> 282000 | O6: 90000 | P6: 38400 | Q6: =SUMIFS(通路月營運!$N$2:$N$2509,通路月營運!$B$2:$B$2509,$B6,通路月營運!$C$2:$C$2509,$C6,通路月營運!$D$2:$D$2509,$D6) -> 175362 | R6: =SUM(L6:Q6) -> 1517862 | S6: =J6-R6 -> 52038 | T6: =IF(J6=0,0,S6/J6) -> 0.033147334 | U6: =IF(H6=0,0,J6/H6) -> 50641.935 | V6: =IF(H6=0,0,K6/H6) -> 170.87097 | W6: =IF(K6=0,0,J6/K6) -> 296.37531 | X6: =IF(J6=0,0,L6/J6) -> 0.33626346 | Y6: =IF(J6=0,0,M6/J6) -> 0.25746863 | Z6: =IF(I6=0,0,J6/I6) -> 17064.13
A7: =TEXT(B7,"0")&"-"&TEXT(C7,"00") -> 2024-01 | B7: 2024 | C7: 1 | D7: NT02 | E7: =INDEX(門市主檔!$B$2:$B$25,MATCH($D7,門市主檔!$A$2:$A$25,0)) -> 新北新莊店 | F7: =INDEX(門市主檔!$C$2:$C$25,MATCH($D7,門市主檔!$A$2:$A$25,0)) -> 北區 | G7: =INDEX(門市主檔!$E$2:$E$25,MATCH($D7,門市主檔!$A$2:$A$25,0)) -> 標準店 | H7: 31 | I7: =SUMIFS(門市年度設定!$E$2:$E$63,門市年度設定!$A$2:$A$63,$B7,門市年度設定!$B$2:$B$63,$D7) -> 76 | J7: =SUMIFS(通路月營運!$I$2:$I$2509,通路月營運!$B$2:$B$2509,$B7,通路月營運!$C$2:$C$2509,$C7,通路月營運!$D$2:$D$2509,$D7) -> 1365400 | K7: =SUMIFS(通路月營運!$K$2:$K$2509,通路月營運!$B$2:$B$2509,$B7,通路月營運!$C$2:$C$2509,$C7,通路月營運!$D$2:$D$2509,$D7) -> 4935 | L7: 416400 | M7: 332500 | N7: =SUMIFS(門市年度設定!$F$2:$F$63,門市年度設定!$A$2:$A$63,$B7,門市年度設定!$B$2:$B$63,$D7) -> 239000 | O7: 78500 | P7: 25400 | Q7: =SUMIFS(通路月營運!$N$2:$N$2509,通路月營運!$B$2:$B$2509,$B7,通路月營運!$C$2:$C$2509,$C7,通路月營運!$D$2:$D$2509,$D7) -> 148104 | R7: =SUM(L7:Q7) -> 1239904 | S7: =J7-R7 -> 125496 | T7: =IF(J7=0,0,S7/J7) -> 0.091911528 | U7: =IF(H7=0,0,J7/H7) -> 44045.161 | V7: =IF(H7=0,0,K7/H7) -> 159.19355 | W7: =IF(K7=0,0,J7/K7) -> 276.6768 | X7: =IF(J7=0,0,L7/J7) -> 0.30496558 | Y7: =IF(J7=0,0,M7/J7) -> 0.24351838 | Z7: =IF(I7=0,0,J7/I7) -> 17965.789
A8: =TEXT(B8,"0")&"-"&TEXT(C8,"00") -> 2024-01 | B8: 2024 | C8: 1 | D8: NT03 | E8: =INDEX(門市主檔!$B$2:$B$25,MATCH($D8,門市主檔!$A$2:$A$25,0)) -> 新北三重店 | F8: =INDEX(門市主檔!$C$2:$C$25,MATCH($D8,門市主檔!$A$2:$A$25,0)) -> 北區 | G8: =INDEX(門市主檔!$E$2:$E$25,MATCH($D8,門市主檔!$A$2:$A$25,0)) -> 小型店 | H8: 31 | I8: =SUMIFS(門市年度設定!$E$2:$E$63,門市年度設定!$A$2:$A$63,$B8,門市年度設定!$B$2:$B$63,$D8) -> 50 | J8: =SUMIFS(通路月營運!$I$2:$I$2509,通路月營運!$B$2:$B$2509,$B8,通路月營運!$C$2:$C$2509,$C8,通路月營運!$D$2:$D$2509,$D8) -> 947400 | K8: =SUMIFS(通路月營運!$K$2:$K$2509,通路月營運!$B$2:$B$2509,$B8,通路月營運!$C$2:$C$2509,$C8,通路月營運!$D$2:$D$2509,$D8) -> 3411 | L8: 316900 | M8: 229900 | N8: =SUMIFS(門市年度設定!$F$2:$F$63,門市年度設定!$A$2:$A$63,$B8,門市年度設定!$B$2:$B$63,$D8) -> 113000 | O8: 50300 | P8: 24300 | Q8: =SUMIFS(通路月營運!$N$2:$N$2509,通路月營運!$B$2:$B$2509,$B8,通路月營運!$C$2:$C$2509,$C8,通路月營運!$D$2:$D$2509,$D8) -> 126258 | R8: =SUM(L8:Q8) -> 860658 | S8: =J8-R8 -> 86742 | T8: =IF(J8=0,0,S8/J8) -> 0.091557948 | U8: =IF(H8=0,0,J8/H8) -> 30561.29 | V8: =IF(H8=0,0,K8/H8) -> 110.03226 | W8: =IF(K8=0,0,J8/K8) -> 277.74846 | X8: =IF(J8=0,0,L8/J8) -> 0.33449441 | Y8: =IF(J8=0,0,M8/J8) -> 0.24266413 | Z8: =IF(I8=0,0,J8/I8) -> 18948
A9: =TEXT(B9,"0")&"-"&TEXT(C9,"00") -> 2024-01 | B9: 2024 | C9: 1 | D9: TC01 | E9: =INDEX(門市主檔!$B$2:$B$25,MATCH($D9,門市主檔!$A$2:$A$25,0)) -> 台中逢甲店 | F9: =INDEX(門市主檔!$C$2:$C$25,MATCH($D9,門市主檔!$A$2:$A$25,0)) -> 中區 | G9: =INDEX(門市主檔!$E$2:$E$25,MATCH($D9,門市主檔!$A$2:$A$25,0)) -> 標準店 | H9: 31 | I9: =SUMIFS(門市年度設定!$E$2:$E$63,門市年度設定!$A$2:$A$63,$B9,門市年度設定!$B$2:$B$63,$D9) -> 83 | J9: =SUMIFS(通路月營運!$I$2:$I$2509,通路月營運!$B$2:$B$2509,$B9,通路月營運!$C$2:$C$2509,$C9,通路月營運!$D$2:$D$2509,$D9) -> 1615200 | K9: =SUMIFS(通路月營運!$K$2:$K$2509,通路月營運!$B$2:$B$2509,$B9,通路月營運!$C$2:$C$2509,$C9,通路月營運!$D$2:$D$2509,$D9) -> 5935 | L9: 530900 | M9: 394100 | N9: =SUMIFS(門市年度設定!$F$2:$F$63,門市年度設定!$A$2:$A$63,$B9,門市年度設定!$B$2:$B$63,$D9) -> 316000 | O9: 109500 | P9: 34700 | Q9: =SUMIFS(通路月營運!$N$2:$N$2509,通路月營運!$B$2:$B$2509,$B9,通路月營運!$C$2:$C$2509,$C9,通路月營運!$D$2:$D$2509,$D9) -> 178728 | R9: =SUM(L9:Q9) -> 1563928 | S9: =J9-R9 -> 51272 | T9: =IF(J9=0,0,S9/J9) -> 0.031743437 | U9: =IF(H9=0,0,J9/H9) -> 52103.226 | V9: =IF(H9=0,0,K9/H9) -> 191.45161 | W9: =IF(K9=0,0,J9/K9) -> 272.14827 | X9: =IF(J9=0,0,L9/J9) -> 0.32868995 | Y9: =IF(J9=0,0,M9/J9) -> 0.24399455 | Z9: =IF(I9=0,0,J9/I9) -> 19460.241
A10: =TEXT(B10,"0")&"-"&TEXT(C10,"00") -> 2024-01 | B10: 2024 | C10: 1 | D10: TC02 | E10: =INDEX(門市主檔!$B$2:$B$25,MATCH($D10,門市主檔!$A$2:$A$25,0)) -> 台中七期店 | F10: =INDEX(門市主檔!$C$2:$C$25,MATCH($D10,門市主檔!$A$2:$A$25,0)) -> 中區 | G10: =INDEX(門市主檔!$E$2:$E$25,MATCH($D10,門市主檔!$A$2:$A$25,0)) -> 旗艦店 | H10: 31 | I10: =SUMIFS(門市年度設定!$E$2:$E$63,門市年度設定!$A$2:$A$63,$B10,門市年度設定!$B$2:$B$63,$D10) -> 124 | J10: =SUMIFS(通路月營運!$I$2:$I$2509,通路月營運!$B$2:$B$2509,$B10,通路月營運!$C$2:$C$2509,$C10,通路月營運!$D$2:$D$2509,$D10) -> 1754800 | K10: =SUMIFS(通路月營運!$K$2:$K$2509,通路月營運!$B$2:$B$2509,$B10,通路月營運!$C$2:$C$2509,$C10,通路月營運!$D$2:$D$2509,$D10) -> 6162 | L10: 603000 | M10: 470200 | N10: =SUMIFS(門市年度設定!$F$2:$F$63,門市年度設定!$A$2:$A$63,$B10,門市年度設定!$B$2:$B$63,$D10) -> 474000 | O10: 118100 | P10: 57200 | Q10: =SUMIFS(通路月營運!$N$2:$N$2509,通路月營運!$B$2:$B$2509,$B10,通路月營運!$C$2:$C$2509,$C10,通路月營運!$D$2:$D$2509,$D10) -> 171336 | R10: =SUM(L10:Q10) -> 1893836 | S10: =J10-R10 -> -139036 | T10: =IF(J10=0,0,S10/J10) -> -0.079231821 | U10: =IF(H10=0,0,J10/H10) -> 56606.452 | V10: =IF(H10=0,0,K10/H10) -> 198.77419 | W10: =IF(K10=0,0,J10/K10) -> 284.77767 | X10: =IF(J10=0,0,L10/J10) -> 0.3436289 | Y10: =IF(J10=0,0,M10/J10) -> 0.26795076 | Z10: =IF(I10=0,0,J10/I10) -> 14151.613
A11: =TEXT(B11,"0")&"-"&TEXT(C11,"00") -> 2024-01 | B11: 2024 | C11: 1 | D11: TC03 | E11: =INDEX(門市主檔!$B$2:$B$25,MATCH($D11,門市主檔!$A$2:$A$25,0)) -> 台中一中店 | F11: =INDEX(門市主檔!$C$2:$C$25,MATCH($D11,門市主檔!$A$2:$A$25,0)) -> 中區 | G11: =INDEX(門市主檔!$E$2:$E$25,MATCH($D11,門市主檔!$A$2:$A$25,0)) -> 小型店 | H11: 31 | I11: =SUMIFS(門市年度設定!$E$2:$E$63,門市年度設定!$A$2:$A$63,$B11,門市年度設定!$B$2:$B$63,$D11) -> 52 | J11: =SUMIFS(通路月營運!$I$2:$I$2509,通路月營運!$B$2:$B$2509,$B11,通路月營運!$C$2:$C$2509,$C11,通路月營運!$D$2:$D$2509,$D11) -> 1179000 | K11: =SUMIFS(通路月營運!$K$2:$K$2509,通路月營運!$B$2:$B$2509,$B11,通路月營運!$C$2:$C$2509,$C11,通路月營運!$D$2:$D$2509,$D11) -> 4407 | L11: 372200 | M11: 313500 | N11: =SUMIFS(門市年度設定!$F$2:$F$63,門市年度設定!$A$2:$A$63,$B11,門市年度設定!$B$2:$B$63,$D11) -> 102000 | O11: 67900 | P11: 19200 | Q11: =SUMIFS(通路月營運!$N$2:$N$2509,通路月營運!$B$2:$B$2509,$B11,通路月營運!$C$2:$C$2509,$C11,通路月營運!$D$2:$D$2509,$D11) -> 155892 | R11: =SUM(L11:Q11) -> 1030692 | S11: =J11-R11 -> 148308 | T11: =IF(J11=0,0,S11/J11) -> 0.12579135 | U11: =IF(H11=0,0,J11/H11) -> 38032.258 | V11: =IF(H11=0,0,K11/H11) -> 142.16129 | W11: =IF(K11=0,0,J11/K11) -> 267.52893 | X11: =IF(J11=0,0,L11/J11) -> 0.31569126 | Y11: =IF(J11=0,0,M11/J11) -> 0.26590331 | Z11: =IF(I11=0,0,J11/I11) -> 22673.077
A12: =TEXT(B12,"0")&"-"&TEXT(C12,"00") -> 2024-01 | B12: 2024 | C12: 1 | D12: TN01 | E12: =INDEX(門市主檔!$B$2:$B$25,MATCH($D12,門市主檔!$A$2:$A$25,0)) -> 台南中西店 | F12: =INDEX(門市主檔!$C$2:$C$25,MATCH($D12,門市主檔!$A$2:$A$25,0)) -> 南區 | G12: =INDEX(門市主檔!$E$2:$E$25,MATCH($D12,門市主檔!$A$2:$A$25,0)) -> 標準店 | H12: 31 | I12: =SUMIFS(門市年度設定!$E$2:$E$63,門市年度設定!$A$2:$A$63,$B12,門市年度設定!$B$2:$B$63,$D12) -> 76 | J12: =SUMIFS(通路月營運!$I$2:$I$2509,通路月營運!$B$2:$B$2509,$B12,通路月營運!$C$2:$C$2509,$C12,通路月營運!$D$2:$D$2509,$D12) -> 1308400 | K12: =SUMIFS(通路月營運!$K$2:$K$2509,通路月營運!$B$2:$B$2509,$B12,通路月營運!$C$2:$C$2509,$C12,通路月營運!$D$2:$D$2509,$D12) -> 4744 | L12: 440700 | M12: 347100 | N12: =SUMIFS(門市年度設定!$F$2:$F$63,門市年度設定!$A$2:$A$63,$B12,門市年度設定!$B$2:$B$63,$D12) -> 205000 | O12: 77500 | P12: 30500 | Q12: =SUMIFS(通路月營運!$N$2:$N$2509,通路月營運!$B$2:$B$2509,$B12,通路月營運!$C$2:$C$2509,$C12,通路月營運!$D$2:$D$2509,$D12) -> 139293 | R12: =SUM(L12:Q12) -> 1240093 | S12: =J12-R12 -> 68307 | T12: =IF(J12=0,0,S12/J12) -> 0.052206512 | U12: =IF(H12=0,0,J12/H12) -> 42206.452 | V12: =IF(H12=0,0,K12/H12) -> 153.03226 | W12: =IF(K12=0,0,J12/K12) -> 275.80101 | X12: =IF(J12=0,0,L12/J12) -> 0.3368236 | Y12: =IF(J12=0,0,M12/J12) -> 0.26528585 | Z12: =IF(I12=0,0,J12/I12) -> 17215.789
A13: =TEXT(B13,"0")&"-"&TEXT(C13,"00") -> 2024-01 | B13: 2024 | C13: 1 | D13: TN02 | E13: =INDEX(門市主檔!$B$2:$B$25,MATCH($D13,門市主檔!$A$2:$A$25,0)) -> 台南東寧店 | F13: =INDEX(門市主檔!$C$2:$C$25,MATCH($D13,門市主檔!$A$2:$A$25,0)) -> 南區 | G13: =INDEX(門市主檔!$E$2:$E$25,MATCH($D13,門市主檔!$A$2:$A$25,0)) -> 小型店 | H13: 31 | I13: =SUMIFS(門市年度設定!$E$2:$E$63,門市年度設定!$A$2:$A$63,$B13,門市年度設定!$B$2:$B$63,$D13) -> 51 | J13: =SUMIFS(通路月營運!$I$2:$I$2509,通路月營運!$B$2:$B$2509,$B13,通路月營運!$C$2:$C$2509,$C13,通路月營運!$D$2:$D$2509,$D13) -> 919200 | K13: =SUMIFS(通路月營運!$K$2:$K$2509,通路月營運!$B$2:$B$2509,$B13,通路月營運!$C$2:$C$2509,$C13,通路月營運!$D$2:$D$2509,$D13) -> 3148 | L13: 313400 | M13: 217200 | N13: =SUMIFS(門市年度設定!$F$2:$F$63,門市年度設定!$A$2:$A$63,$B13,門市年度設定!$B$2:$B$63,$D13) -> 91000 | O13: 62900 | P13: 20400 | Q13: =SUMIFS(通路月營運!$N$2:$N$2509,通路月營運!$B$2:$B$2509,$B13,通路月營運!$C$2:$C$2509,$C13,通路月營運!$D$2:$D$2509,$D13) -> 120120 | R13: =SUM(L13:Q13) -> 825020 | S13: =J13-R13 -> 94180 | T13: =IF(J13=0,0,S13/J13) -> 0.10245866 | U13: =IF(H13=0,0,J13/H13) -> 29651.613 | V13: =IF(H13=0,0,K13/H13) -> 101.54839 | W13: =IF(K13=0,0,J13/K13) -> 291.99492 | X13: =IF(J13=0,0,L13/J13) -> 0.34094865 | Y13: =IF(J13=0,0,M13/J13) -> 0.23629243 | Z13: =IF(I13=0,0,J13/I13) -> 18023.529
... A643: =TEXT(B643,"0")&"-"&TEXT(C643,"00") -> 2026-09 | B643: 2026 | C643: 9 | D643: YL01 | E643: =INDEX(門市主檔!$B$2:$B$25,MATCH($D643,門市主檔!$A$2:$A$25,0)) -> 雲林斗六店 | F643: =INDEX(門市主檔!$C$2:$C$25,MATCH($D643,門市主檔!$A$2:$A$25,0)) -> 中區 | G643: =INDEX(門市主檔!$E$2:$E$25,MATCH($D643,門市主檔!$A$2:$A$25,0)) -> 標準店 | H643: 30 | I643: =SUMIFS(門市年度設定!$E$2:$E$63,門市年度設定!$A$2:$A$63,$B643,門市年度設定!$B$2:$B$63,$D643) -> 90 | J643: =SUMIFS(通路月營運!$I$2:$I$2509,通路月營運!$B$2:$B$2509,$B643,通路月營運!$C$2:$C$2509,$C643,通路月營運!$D$2:$D$2509,$D643) -> 1661100 | K643: =SUMIFS(通路月營運!$K$2:$K$2509,通路月營運!$B$2:$B$2509,$B643,通路月營運!$C$2:$C$2509,$C643,通路月營運!$D$2:$D$2509,$D643) -> 5573 | L643: 505600 | M643: 463900 | N643: =SUMIFS(門市年度設定!$F$2:$F$63,門市年度設定!$A$2:$A$63,$B643,門市年度設定!$B$2:$B$63,$D643) -> 170000 | O643: 97900 | P643: 35900 | Q643: =SUMIFS(通路月營運!$N$2:$N$2509,通路月營運!$B$2:$B$2509,$B643,通路月營運!$C$2:$C$2509,$C643,通路月營運!$D$2:$D$2509,$D643) -> 182091 | R643: =SUM(L643:Q643) -> 1455391 | S643: =J643-R643 -> 205709 | T643: =IF(J643=0,0,S643/J643) -> 0.12383902 | U643: =IF(H643=0,0,J643/H643) -> 55370 | V643: =IF(H643=0,0,K643/H643) -> 185.76667 | W643: =IF(K643=0,0,J643/K643) -> 298.06209 | X643: =IF(J643=0,0,L643/J643) -> 0.30437662 | Y643: =IF(J643=0,0,M643/J643) -> 0.27927277 | Z643: =IF(I643=0,0,J643/I643) -> 18456.667

Sheet 品項月銷售
A1: 年月 | B1: 年 | C1: 月 | D1: 門市代號 | E1: 品項代號 | F1: 品項名稱 | G1: 品項類別 | H1: 當年售價 | I1: 銷售份數 | J1: 銷售金額
A2: =TEXT(B2,"0")&"-"&TEXT(C2,"00") -> 2024-01 | B2: 2024 | C2: 1 | D2: CH01 | E2: MI01 | F2: =INDEX(品項主檔!$B$2:$B$11,MATCH($E2,品項主檔!$A$2:$A$11,0)) -> 招牌牛肉麵 | G2: =INDEX(品項主檔!$C$2:$C$11,MATCH($E2,品項主檔!$A$2:$A$11,0)) -> 主食 | H2: =SUMIFS(品項年度售價!$D$2:$D$31,品項年度售價!$A$2:$A$31,$B2,品項年度售價!$B$2:$B$31,$E2) -> 280 | I2: 163 | J2: =H2*I2 -> 45640
A3: =TEXT(B3,"0")&"-"&TEXT(C3,"00") -> 2024-01 | B3: 2024 | C3: 1 | D3: CH01 | E3: MI02 | F3: =INDEX(品項主檔!$B$2:$B$11,MATCH($E3,品項主檔!$A$2:$A$11,0)) -> 三杯雞定食 | G3: =INDEX(品項主檔!$C$2:$C$11,MATCH($E3,品項主檔!$A$2:$A$11,0)) -> 主食 | H3: =SUMIFS(品項年度售價!$D$2:$D$31,品項年度售價!$A$2:$A$31,$B3,品項年度售價!$B$2:$B$31,$E3) -> 260 | I3: 162 | J3: =H3*I3 -> 42120
A4: =TEXT(B4,"0")&"-"&TEXT(C4,"00") -> 2024-01 | B4: 2024 | C4: 1 | D4: CH01 | E4: MI03 | F4: =INDEX(品項主檔!$B$2:$B$11,MATCH($E4,品項主檔!$A$2:$A$11,0)) -> 蔥油雞腿飯 | G4: =INDEX(品項主檔!$C$2:$C$11,MATCH($E4,品項主檔!$A$2:$A$11,0)) -> 主食 | H4: =SUMIFS(品項年度售價!$D$2:$D$31,品項年度售價!$A$2:$A$31,$B4,品項年度售價!$B$2:$B$31,$E4) -> 220 | I4: 173 | J4: =H4*I4 -> 38060
A5: =TEXT(B5,"0")&"-"&TEXT(C5,"00") -> 2024-01 | B5: 2024 | C5: 1 | D5: CH01 | E5: MI04 | F5: =INDEX(品項主檔!$B$2:$B$11,MATCH($E5,品項主檔!$A$2:$A$11,0)) -> 黑胡椒豬排飯 | G5: =INDEX(品項主檔!$C$2:$C$11,MATCH($E5,品項主檔!$A$2:$A$11,0)) -> 主食 | H5: =SUMIFS(品項年度售價!$D$2:$D$31,品項年度售價!$A$2:$A$31,$B5,品項年度售價!$B$2:$B$31,$E5) -> 230 | I5: 193 | J5: =H5*I5 -> 44390
A6: =TEXT(B6,"0")&"-"&TEXT(C6,"00") -> 2024-01 | B6: 2024 | C6: 1 | D6: CH01 | E6: MI05 | F6: =INDEX(品項主檔!$B$2:$B$11,MATCH($E6,品項主檔!$A$2:$A$11,0)) -> 麻油雞湯麵 | G6: =INDEX(品項主檔!$C$2:$C$11,MATCH($E6,品項主檔!$A$2:$A$11,0)) -> 主食 | H6: =SUMIFS(品項年度售價!$D$2:$D$31,品項年度售價!$A$2:$A$31,$B6,品項年度售價!$B$2:$B$31,$E6) -> 290 | I6: 204 | J6: =H6*I6 -> 59160
A7: =TEXT(B7,"0")&"-"&TEXT(C7,"00") -> 2024-01 | B7: 2024 | C7: 1 | D7: CH01 | E7: MI06 | F7: =INDEX(品項主檔!$B$2:$B$11,MATCH($E7,品項主檔!$A$2:$A$11,0)) -> 塔香涼麵 | G7: =INDEX(品項主檔!$C$2:$C$11,MATCH($E7,品項主檔!$A$2:$A$11,0)) -> 主食 | H7: =SUMIFS(品項年度售價!$D$2:$D$31,品項年度售價!$A$2:$A$31,$B7,品項年度售價!$B$2:$B$31,$E7) -> 180 | I7: 77 | J7: =H7*I7 -> 13860
A8: =TEXT(B8,"0")&"-"&TEXT(C8,"00") -> 2024-01 | B8: 2024 | C8: 1 | D8: CH01 | E8: MI07 | F8: =INDEX(品項主檔!$B$2:$B$11,MATCH($E8,品項主檔!$A$2:$A$11,0)) -> 海鮮炒飯 | G8: =INDEX(品項主檔!$C$2:$C$11,MATCH($E8,品項主檔!$A$2:$A$11,0)) -> 主食 | H8: =SUMIFS(品項年度售價!$D$2:$D$31,品項年度售價!$A$2:$A$31,$B8,品項年度售價!$B$2:$B$31,$E8) -> 250 | I8: 165 | J8: =H8*I8 -> 41250
A9: =TEXT(B9,"0")&"-"&TEXT(C9,"00") -> 2024-01 | B9: 2024 | C9: 1 | D9: CH01 | E9: MI08 | F9: =INDEX(品項主檔!$B$2:$B$11,MATCH($E9,品項主檔!$A$2:$A$11,0)) -> 酸辣湯 | G9: =INDEX(品項主檔!$C$2:$C$11,MATCH($E9,品項主檔!$A$2:$A$11,0)) -> 湯品 | H9: =SUMIFS(品項年度售價!$D$2:$D$31,品項年度售價!$A$2:$A$31,$B9,品項年度售價!$B$2:$B$31,$E9) -> 60 | I9: 913 | J9: =H9*I9 -> 54780
A10: =TEXT(B10,"0")&"-"&TEXT(C10,"00") -> 2024-01 | B10: 2024 | C10: 1 | D10: CH01 | E10: MI09 | F10: =INDEX(品項主檔!$B$2:$B$11,MATCH($E10,品項主檔!$A$2:$A$11,0)) -> 招牌滷味拼盤 | G10: =INDEX(品項主檔!$C$2:$C$11,MATCH($E10,品項主檔!$A$2:$A$11,0)) -> 小菜 | H10: =SUMIFS(品項年度售價!$D$2:$D$31,品項年度售價!$A$2:$A$31,$B10,品項年度售價!$B$2:$B$31,$E10) -> 120 | I10: 592 | J10: =H10*I10 -> 71040
A11: =TEXT(B11,"0")&"-"&TEXT(C11,"00") -> 2024-01 | B11: 2024 | C11: 1 | D11: CH01 | E11: MI10 | F11: =INDEX(品項主檔!$B$2:$B$11,MATCH($E11,品項主檔!$A$2:$A$11,0)) -> 古早味紅茶 | G11: =INDEX(品項主檔!$C$2:$C$11,MATCH($E11,品項主檔!$A$2:$A$11,0)) -> 飲品 | H11: =SUMIFS(品項年度售價!$D$2:$D$31,品項年度售價!$A$2:$A$31,$B11,品項年度售價!$B$2:$B$31,$E11) -> 45 | I11: 1196 | J11: =H11*I11 -> 53820
A12: =TEXT(B12,"0")&"-"&TEXT(C12,"00") -> 2024-01 | B12: 2024 | C12: 1 | D12: HC01 | E12: MI01 | F12: =INDEX(品項主檔!$B$2:$B$11,MATCH($E12,品項主檔!$A$2:$A$11,0)) -> 招牌牛肉麵 | G12: =INDEX(品項主檔!$C$2:$C$11,MATCH($E12,品項主檔!$A$2:$A$11,0)) -> 主食 | H12: =SUMIFS(品項年度售價!$D$2:$D$31,品項年度售價!$A$2:$A$31,$B12,品項年度售價!$B$2:$B$31,$E12) -> 280 | I12: 514 | J12: =H12*I12 -> 143920
A13: =TEXT(B13,"0")&"-"&TEXT(C13,"00") -> 2024-01 | B13: 2024 | C13: 1 | D13: HC01 | E13: MI02 | F13: =INDEX(品項主檔!$B$2:$B$11,MATCH($E13,品項主檔!$A$2:$A$11,0)) -> 三杯雞定食 | G13: =INDEX(品項主檔!$C$2:$C$11,MATCH($E13,品項主檔!$A$2:$A$11,0)) -> 主食 | H13: =SUMIFS(品項年度售價!$D$2:$D$31,品項年度售價!$A$2:$A$31,$B13,品項年度售價!$B$2:$B$31,$E13) -> 260 | I13: 389 | J13: =H13*I13 -> 101140
... A6421: =TEXT(B6421,"0")&"-"&TEXT(C6421,"00") -> 2026-09 | B6421: 2026 | C6421: 9 | D6421: YL01 | E6421: MI10 | F6421: =INDEX(品項主檔!$B$2:$B$11,MATCH($E6421,品項主檔!$A$2:$A$11,0)) -> 古早味紅茶 | G6421: =INDEX(品項主檔!$C$2:$C$11,MATCH($E6421,品項主檔!$A$2:$A$11,0)) -> 飲品 | H6421: =SUMIFS(品項年度售價!$D$2:$D$31,品項年度售價!$A$2:$A$31,$B6421,品項年度售價!$B$2:$B$31,$E6421) -> 45 | I6421: 3641 | J6421: =H6421*I6421 -> 163845

Sheet 門市年度彙總
A1: 年度 | B1: 門市代號 | C1: 門市名稱 | D1: 區域 | E1: 店型 | F1: 營業月數 | G1: 營業天數 | H1: 營業額 | I1: 總成本 | J1: 營業利益 | K1: 營業利益率 | L1: 來客數 | M1: 平均客單價 | N1: 日均營業額 | O1: 食材成本率 | P1: 人事成本率 | Q1: 外送抽成佔營收比 | R1: 外送營收佔比
A2: 2024 | B2: CH01 | C2: =INDEX(門市主檔!$B$2:$B$25,MATCH($B2,門市主檔!$A$2:$A$25,0)) -> 彰化員林店 | D2: =INDEX(門市主檔!$C$2:$C$25,MATCH($B2,門市主檔!$A$2:$A$25,0)) -> 中區 | E2: =INDEX(門市主檔!$E$2:$E$25,MATCH($B2,門市主檔!$A$2:$A$25,0)) -> 小型店 | F2: =COUNTIFS(月營運明細!$B$2:$B$643,$A2,月營運明細!$D$2:$D$643,$B2) -> 11 | G2: =SUMIFS(月營運明細!$H$2:$H$643,月營運明細!$B$2:$B$643,$A2,月營運明細!$D$2:$D$643,$B2) -> 335 | H2: =SUMIFS(月營運明細!$J$2:$J$643,月營運明細!$B$2:$B$643,$A2,月營運明細!$D$2:$D$643,$B2) -> 13363600 | I2: =SUMIFS(月營運明細!$R$2:$R$643,月營運明細!$B$2:$B$643,$A2,月營運明細!$D$2:$D$643,$B2) -> 11417358 | J2: =H2-I2 -> 1946242 | K2: =IF(H2=0,0,J2/H2) -> 0.14563755 | L2: =SUMIFS(月營運明細!$K$2:$K$643,月營運明細!$B$2:$B$643,$A2,月營運明細!$D$2:$D$643,$B2) -> 47618 | M2: =IF(L2=0,0,H2/L2) -> 280.64177 | N2: =IF(G2=0,0,H2/G2) -> 39891.343 | O2: =IF(H2=0,0,SUMIFS(月營運明細!$L$2:$L$643,月營運明細!$B$2:$B$643,$A2,月營運明細!$D$2:$D$643,$B2)/H2) -> 0.30981173 | P2: =IF(H2=0,0,SUMIFS(月營運明細!$M$2:$M$643,月營運明細!$B$2:$B$643,$A2,月營運明細!$D$2:$D$643,$B2)/H2) -> 0.25598641 | Q2: =IF(H2=0,0,SUMIFS(月營運明細!$Q$2:$Q$643,月營運明細!$B$2:$B$643,$A2,月營運明細!$D$2:$D$643,$B2)/H2) -> 0.13118905 | R2: =IF(H2=0,0,SUMIFS(通路月營運!$I$2:$I$2509,通路月營運!$B$2:$B$2509,$A2,通路月營運!$D$2:$D$2509,$B2,通路月營運!$H$2:$H$2509,"外送平台")/H2) -> 0.39754258
A3: 2024 | B3: HC01 | C3: =INDEX(門市主檔!$B$2:$B$25,MATCH($B3,門市主檔!$A$2:$A$25,0)) -> 新竹巨城店 | D3: =INDEX(門市主檔!$C$2:$C$25,MATCH($B3,門市主檔!$A$2:$A$25,0)) -> 北區 | E3: =INDEX(門市主檔!$E$2:$E$25,MATCH($B3,門市主檔!$A$2:$A$25,0)) -> 旗艦店 | F3: =COUNTIFS(月營運明細!$B$2:$B$643,$A3,月營運明細!$D$2:$D$643,$B3) -> 12 | G3: =SUMIFS(月營運明細!$H$2:$H$643,月營運明細!$B$2:$B$643,$A3,月營運明細!$D$2:$D$643,$B3) -> 366 | H3: =SUMIFS(月營運明細!$J$2:$J$643,月營運明細!$B$2:$B$643,$A3,月營運明細!$D$2:$D$643,$B3) -> 30791000 | I3: =SUMIFS(月營運明細!$R$2:$R$643,月營運明細!$B$2:$B$643,$A3,月營運明細!$D$2:$D$643,$B3) -> 29534358 | J3: =H3-I3 -> 1256642 | K3: =IF(H3=0,0,J3/H3) -> 0.040811991 | L3: =SUMIFS(月營運明細!$K$2:$K$643,月營運明細!$B$2:$B$643,$A3,月營運明細!$D$2:$D$643,$B3) -> 103500 | M3: =IF(L3=0,0,H3/L3) -> 297.49758 | N3: =IF(G3=0,0,H3/G3) -> 84128.415 | O3: =IF(H3=0,0,SUMIFS(月營運明細!$L$2:$L$643,月營運明細!$B$2:$B$643,$A3,月營運明細!$D$2:$D$643,$B3)/H3) -> 0.32722549 | P3: =IF(H3=0,0,SUMIFS(月營運明細!$M$2:$M$643,月營運明細!$B$2:$B$643,$A3,月營運明細!$D$2:$D$643,$B3)/H3) -> 0.25733169 | Q3: =IF(H3=0,0,SUMIFS(月營運明細!$Q$2:$Q$643,月營運明細!$B$2:$B$643,$A3,月營運明細!$D$2:$D$643,$B3)/H3) -> 0.092197655 | R3: =IF(H3=0,0,SUMIFS(通路月營運!$I$2:$I$2509,通路月營運!$B$2:$B$2509,$A3,通路月營運!$D$2:$D$2509,$B3,通路月營運!$H$2:$H$2509,"外送平台")/H3) -> 0.27938683
A4: 2024 | B4: KH01 | C4: =INDEX(門市主檔!$B$2:$B$25,MATCH($B4,門市主檔!$A$2:$A$25,0)) -> 高雄左營店 | D4: =INDEX(門市主檔!$C$2:$C$25,MATCH($B4,門市主檔!$A$2:$A$25,0)) -> 南區 | E4: =INDEX(門市主檔!$E$2:$E$25,MATCH($B4,門市主檔!$A$2:$A$25,0)) -> 旗艦店 | F4: =COUNTIFS(月營運明細!$B$2:$B$643,$A4,月營運明細!$D$2:$D$643,$B4) -> 12 | G4: =SUMIFS(月營運明細!$H$2:$H$643,月營運明細!$B$2:$B$643,$A4,月營運明細!$D$2:$D$643,$B4) -> 366 | H4: =SUMIFS(月營運明細!$J$2:$J$643,月營運明細!$B$2:$B$643,$A4,月營運明細!$D$2:$D$643,$B4) -> 26320100 | I4: =SUMIFS(月營運明細!$R$2:$R$643,月營運明細!$B$2:$B$643,$A4,月營運明細!$D$2:$D$643,$B4) -> 25345856 | J4: =H4-I4 -> 974244 | K4: =IF(H4=0,0,J4/H4) -> 0.037015209 | L4: =SUMIFS(月營運明細!$K$2:$K$643,月營運明細!$B$2:$B$643,$A4,月營運明細!$D$2:$D$643,$B4) -> 91492 | M4: =IF(L4=0,0,H4/L4) -> 287.67652 | N4: =IF(G4=0,0,H4/G4) -> 71912.842 | O4: =IF(H4=0,0,SUMIFS(月營運明細!$L$2:$L$643,月營運明細!$B$2:$B$643,$A4,月營運明細!$D$2:$D$643,$B4)/H4) -> 0.32361199 | P4: =IF(H4=0,0,SUMIFS(月營運明細!$M$2:$M$643,月營運明細!$B$2:$B$643,$A4,月營運明細!$D$2:$D$643,$B4)/H4) -> 0.25646939 | Q4: =IF(H4=0,0,SUMIFS(月營運明細!$Q$2:$Q$643,月營運明細!$B$2:$B$643,$A4,月營運明細!$D$2:$D$643,$B4)/H4) -> 0.092068647 | R4: =IF(H4=0,0,SUMIFS(通路月營運!$I$2:$I$2509,通路月營運!$B$2:$B$2509,$A4,通路月營運!$D$2:$D$2509,$B4,通路月營運!$H$2:$H$2509,"外送平台")/H4) -> 0.2789959
A5: 2024 | B5: KH02 | C5: =INDEX(門市主檔!$B$2:$B$25,MATCH($B5,門市主檔!$A$2:$A$25,0)) -> 高雄三多店 | D5: =INDEX(門市主檔!$C$2:$C$25,MATCH($B5,門市主檔!$A$2:$A$25,0)) -> 南區 | E5: =INDEX(門市主檔!$E$2:$E$25,MATCH($B5,門市主檔!$A$2:$A$25,0)) -> 標準店 | F5: =COUNTIFS(月營運明細!$B$2:$B$643,$A5,月營運明細!$D$2:$D$643,$B5) -> 12 | G5: =SUMIFS(月營運明細!$H$2:$H$643,月營運明細!$B$2:$B$643,$A5,月營運明細!$D$2:$D$643,$B5) -> 362 | H5: =SUMIFS(月營運明細!$J$2:$J$643,月營運明細!$B$2:$B$643,$A5,月營運明細!$D$2:$D$643,$B5) -> 21464500 | I5: =SUMIFS(月營運明細!$R$2:$R$643,月營運明細!$B$2:$B$643,$A5,月營運明細!$D$2:$D$643,$B5) -> 18938838 | J5: =H5-I5 -> 2525662 | K5: =IF(H5=0,0,J5/H5) -> 0.11766694 | L5: =SUMIFS(月營運明細!$K$2:$K$643,月營運明細!$B$2:$B$643,$A5,月營運明細!$D$2:$D$643,$B5) -> 74452 | M5: =IF(L5=0,0,H5/L5) -> 288.29984 | N5: =IF(G5=0,0,H5/G5) -> 59294.199 | O5: =IF(H5=0,0,SUMIFS(月營運明細!$L$2:$L$643,月營運明細!$B$2:$B$643,$A5,月營運明細!$D$2:$D$643,$B5)/H5) -> 0.31980246 | P5: =IF(H5=0,0,SUMIFS(月營運明細!$M$2:$M$643,月營運明細!$B$2:$B$643,$A5,月營運明細!$D$2:$D$643,$B5)/H5) -> 0.25580843 | Q5: =IF(H5=0,0,SUMIFS(月營運明細!$Q$2:$Q$643,月營運明細!$B$2:$B$643,$A5,月營運明細!$D$2:$D$643,$B5)/H5) -> 0.10990417 | R5: =IF(H5=0,0,SUMIFS(通路月營運!$I$2:$I$2509,通路月營運!$B$2:$B$2509,$A5,通路月營運!$D$2:$D$2509,$B5,通路月營運!$H$2:$H$2509,"外送平台")/H5) -> 0.33304293
A6: 2024 | B6: NT01 | C6: =INDEX(門市主檔!$B$2:$B$25,MATCH($B6,門市主檔!$A$2:$A$25,0)) -> 新北板橋店 | D6: =INDEX(門市主檔!$C$2:$C$25,MATCH($B6,門市主檔!$A$2:$A$25,0)) -> 北區 | E6: =INDEX(門市主檔!$E$2:$E$25,MATCH($B6,門市主檔!$A$2:$A$25,0)) -> 標準店 | F6: =COUNTIFS(月營運明細!$B$2:$B$643,$A6,月營運明細!$D$2:$D$643,$B6) -> 12 | G6: =SUMIFS(月營運明細!$H$2:$H$643,月營運明細!$B$2:$B$643,$A6,月營運明細!$D$2:$D$643,$B6) -> 366 | H6: =SUMIFS(月營運明細!$J$2:$J$643,月營運明細!$B$2:$B$643,$A6,月營運明細!$D$2:$D$643,$B6) -> 27855000 | I6: =SUMIFS(月營運明細!$R$2:$R$643,月營運明細!$B$2:$B$643,$A6,月營運明細!$D$2:$D$643,$B6) -> 24855719 | J6: =H6-I6 -> 2999281 | K6: =IF(H6=0,0,J6/H6) -> 0.10767478 | L6: =SUMIFS(月營運明細!$K$2:$K$643,月營運明細!$B$2:$B$643,$A6,月營運明細!$D$2:$D$643,$B6) -> 96837 | M6: =IF(L6=0,0,H6/L6) -> 287.64832 | N6: =IF(G6=0,0,H6/G6) -> 76106.557 | O6: =IF(H6=0,0,SUMIFS(月營運明細!$L$2:$L$643,月營運明細!$B$2:$B$643,$A6,月營運明細!$D$2:$D$643,$B6)/H6) -> 0.32415365 | P6: =IF(H6=0,0,SUMIFS(月營運明細!$M$2:$M$643,月營運明細!$B$2:$B$643,$A6,月營運明細!$D$2:$D$643,$B6)/H6) -> 0.25519655 | Q6: =IF(H6=0,0,SUMIFS(月營運明細!$Q$2:$Q$643,月營運明細!$B$2:$B$643,$A6,月營運明細!$D$2:$D$643,$B6)/H6) -> 0.10845159 | R6: =IF(H6=0,0,SUMIFS(通路月營運!$I$2:$I$2509,通路月營運!$B$2:$B$2509,$A6,通路月營運!$D$2:$D$2509,$B6,通路月營運!$H$2:$H$2509,"外送平台")/H6) -> 0.32864118
A7: 2024 | B7: NT02 | C7: =INDEX(門市主檔!$B$2:$B$25,MATCH($B7,門市主檔!$A$2:$A$25,0)) -> 新北新莊店 | D7: =INDEX(門市主檔!$C$2:$C$25,MATCH($B7,門市主檔!$A$2:$A$25,0)) -> 北區 | E7: =INDEX(門市主檔!$E$2:$E$25,MATCH($B7,門市主檔!$A$2:$A$25,0)) -> 標準店 | F7: =COUNTIFS(月營運明細!$B$2:$B$643,$A7,月營運明細!$D$2:$D$643,$B7) -> 12 | G7: =SUMIFS(月營運明細!$H$2:$H$643,月營運明細!$B$2:$B$643,$A7,月營運明細!$D$2:$D$643,$B7) -> 366 | H7: =SUMIFS(月營運明細!$J$2:$J$643,月營運明細!$B$2:$B$643,$A7,月營運明細!$D$2:$D$643,$B7) -> 22823300 | I7: =SUMIFS(月營運明細!$R$2:$R$643,月營運明細!$B$2:$B$643,$A7,月營運明細!$D$2:$D$643,$B7) -> 20485949 | J7: =H7-I7 -> 2337351 | K7: =IF(H7=0,0,J7/H7) -> 0.10241074 | L7: =SUMIFS(月營運明細!$K$2:$K$643,月營運明細!$B$2:$B$643,$A7,月營運明細!$D$2:$D$643,$B7) -> 78509 | M7: =IF(L7=0,0,H7/L7) -> 290.70935 | N7: =IF(G7=0,0,H7/G7) -> 62358.743 | O7: =IF(H7=0,0,SUMIFS(月營運明細!$L$2:$L$643,月營運明細!$B$2:$B$643,$A7,月營運明細!$D$2:$D$643,$B7)/H7) -> 0.31342093 | P7: =IF(H7=0,0,SUMIFS(月營運明細!$M$2:$M$643,月營運明細!$B$2:$B$643,$A7,月營運明細!$D$2:$D$643,$B7)/H7) -> 0.26469441 | Q7: =IF(H7=0,0,SUMIFS(月營運明細!$Q$2:$Q$643,月營運明細!$B$2:$B$643,$A7,月營運明細!$D$2:$D$643,$B7)/H7) -> 0.10822927 | R7: =IF(H7=0,0,SUMIFS(通路月營運!$I$2:$I$2509,通路月營運!$B$2:$B$2509,$A7,通路月營運!$D$2:$D$2509,$B7,通路月營運!$H$2:$H$2509,"外送平台")/H7) -> 0.32796747
A8: 2024 | B8: NT03 | C8: =INDEX(門市主檔!$B$2:$B$25,MATCH($B8,門市主檔!$A$2:$A$25,0)) -> 新北三重店 | D8: =INDEX(門市主檔!$C$2:$C$25,MATCH($B8,門市主檔!$A$2:$A$25,0)) -> 北區 | E8: =INDEX(門市主檔!$E$2:$E$25,MATCH($B8,門市主檔!$A$2:$A$25,0)) -> 小型店 | F8: =COUNTIFS(月營運明細!$B$2:$B$643,$A8,月營運明細!$D$2:$D$643,$B8) -> 12 | G8: =SUMIFS(月營運明細!$H$2:$H$643,月營運明細!$B$2:$B$643,$A8,月營運明細!$D$2:$D$643,$B8) -> 366 | H8: =SUMIFS(月營運明細!$J$2:$J$643,月營運明細!$B$2:$B$643,$A8,月營運明細!$D$2:$D$643,$B8) -> 16981400 | I8: =SUMIFS(月營運明細!$R$2:$R$643,月營運明細!$B$2:$B$643,$A8,月營運明細!$D$2:$D$643,$B8) -> 14858020 | J8: =H8-I8 -> 2123380 | K8: =IF(H8=0,0,J8/H8) -> 0.12504152 | L8: =SUMIFS(月營運明細!$K$2:$K$643,月營運明細!$B$2:$B$643,$A8,月營運明細!$D$2:$D$643,$B8) -> 59586 | M8: =IF(L8=0,0,H8/L8) -> 284.98976 | N8: =IF(G8=0,0,H8/G8) -> 46397.268 | O8: =IF(H8=0,0,SUMIFS(月營運明細!$L$2:$L$643,月營運明細!$B$2:$B$643,$A8,月營運明細!$D$2:$D$643,$B8)/H8) -> 0.32049772 | P8: =IF(H8=0,0,SUMIFS(月營運明細!$M$2:$M$643,月營運明細!$B$2:$B$643,$A8,月營運明細!$D$2:$D$643,$B8)/H8) -> 0.2539131 | Q8: =IF(H8=0,0,SUMIFS(月營運明細!$Q$2:$Q$643,月營運明細!$B$2:$B$643,$A8,月營運明細!$D$2:$D$643,$B8)/H8) -> 0.13222231 | R8: =IF(H8=0,0,SUMIFS(通路月營運!$I$2:$I$2509,通路月營運!$B$2:$B$2509,$A8,通路月營運!$D$2:$D$2509,$B8,通路月營運!$H$2:$H$2509,"外送平台")/H8) -> 0.40067368
A9: 2024 | B9: TC01 | C9: =INDEX(門市主檔!$B$2:$B$25,MATCH($B9,門市主檔!$A$2:$A$25,0)) -> 台中逢甲店 | D9: =INDEX(門市主檔!$C$2:$C$25,MATCH($B9,門市主檔!$A$2:$A$25,0)) -> 中區 | E9: =INDEX(門市主檔!$E$2:$E$25,MATCH($B9,門市主檔!$A$2:$A$25,0)) -> 標準店 | F9: =COUNTIFS(月營運明細!$B$2:$B$643,$A9,月營運明細!$D$2:$D$643,$B9) -> 12 | G9: =SUMIFS(月營運明細!$H$2:$H$643,月營運明細!$B$2:$B$643,$A9,月營運明細!$D$2:$D$643,$B9) -> 366 | H9: =SUMIFS(月營運明細!$J$2:$J$643,月營運明細!$B$2:$B$643,$A9,月營運明細!$D$2:$D$643,$B9) -> 29364100 | I9: =SUMIFS(月營運明細!$R$2:$R$643,月營運明細!$B$2:$B$643,$A9,月營運明細!$D$2:$D$643,$B9) -> 26283667 | J9: =H9-I9 -> 3080433 | K9: =IF(H9=0,0,J9/H9) -> 0.10490473 | L9: =SUMIFS(月營運明細!$K$2:$K$643,月營運明細!$B$2:$B$643,$A9,月營運明細!$D$2:$D$643,$B9) -> 101571 | M9: =IF(L9=0,0,H9/L9) -> 289.09925 | N9: =IF(G9=0,0,H9/G9) -> 80229.781 | O9: =IF(H9=0,0,SUMIFS(月營運明細!$L$2:$L$643,月營運明細!$B$2:$B$643,$A9,月營運明細!$D$2:$D$643,$B9)/H9) -> 0.3191414 | P9: =IF(H9=0,0,SUMIFS(月營運明細!$M$2:$M$643,月營運明細!$B$2:$B$643,$A9,月營運明細!$D$2:$D$643,$B9)/H9) -> 0.25781822 | Q9: =IF(H9=0,0,SUMIFS(月營運明細!$Q$2:$Q$643,月營運明細!$B$2:$B$643,$A9,月營運明細!$D$2:$D$643,$B9)/H9) -> 0.10811048 | R9: =IF(H9=0,0,SUMIFS(通路月營運!$I$2:$I$2509,通路月營運!$B$2:$B$2509,$A9,通路月營運!$D$2:$D$2509,$B9,通路月營運!$H$2:$H$2509,"外送平台")/H9) -> 0.32760752
A10: 2024 | B10: TC02 | C10: =INDEX(門市主檔!$B$2:$B$25,MATCH($B10,門市主檔!$A$2:$A$25,0)) -> 台中七期店 | D10: =INDEX(門市主檔!$C$2:$C$25,MATCH($B10,門市主檔!$A$2:$A$25,0)) -> 中區 | E10: =INDEX(門市主檔!$E$2:$E$25,MATCH($B10,門市主檔!$A$2:$A$25,0)) -> 旗艦店 | F10: =COUNTIFS(月營運明細!$B$2:$B$643,$A10,月營運明細!$D$2:$D$643,$B10) -> 12 | G10: =SUMIFS(月營運明細!$H$2:$H$643,月營運明細!$B$2:$B$643,$A10,月營運明細!$D$2:$D$643,$B10) -> 366 | H10: =SUMIFS(月營運明細!$J$2:$J$643,月營運明細!$B$2:$B$643,$A10,月營運明細!$D$2:$D$643,$B10) -> 27561200 | I10: =SUMIFS(月營運明細!$R$2:$R$643,月營運明細!$B$2:$B$643,$A10,月營運明細!$D$2:$D$643,$B10) -> 26651737 | J10: =H10-I10 -> 909463 | K10: =IF(H10=0,0,J10/H10) -> 0.032997946 | L10: =SUMIFS(月營運明細!$K$2:$K$643,月營運明細!$B$2:$B$643,$A10,月營運明細!$D$2:$D$643,$B10) -> 94453 | M10: =IF(L10=0,0,H10/L10) -> 291.79804 | N10: =IF(G10=0,0,H10/G10) -> 75303.825 | O10: =IF(H10=0,0,SUMIFS(月營運明細!$L$2:$L$643,月營運明細!$B$2:$B$643,$A10,月營運明細!$D$2:$D$643,$B10)/H10) -> 0.32055208 | P10: =IF(H10=0,0,SUMIFS(月營運明細!$M$2:$M$643,月營運明細!$B$2:$B$643,$A10,月營運明細!$D$2:$D$643,$B10)/H10) -> 0.26238698 | Q10: =IF(H10=0,0,SUMIFS(月營運明細!$Q$2:$Q$643,月營運明細!$B$2:$B$643,$A10,月營運明細!$D$2:$D$643,$B10)/H10) -> 0.09373819 | R10: =IF(H10=0,0,SUMIFS(通路月營運!$I$2:$I$2509,通路月營運!$B$2:$B$2509,$A10,通路月營運!$D$2:$D$2509,$B10,通路月營運!$H$2:$H$2509,"外送平台")/H10) -> 0.28405512
A11: 2024 | B11: TC03 | C11: =INDEX(門市主檔!$B$2:$B$25,MATCH($B11,門市主檔!$A$2:$A$25,0)) -> 台中一中店 | D11: =INDEX(門市主檔!$C$2:$C$25,MATCH($B11,門市主檔!$A$2:$A$25,0)) -> 中區 | E11: =INDEX(門市主檔!$E$2:$E$25,MATCH($B11,門市主檔!$A$2:$A$25,0)) -> 小型店 | F11: =COUNTIFS(月營運明細!$B$2:$B$643,$A11,月營運明細!$D$2:$D$643,$B11) -> 12 | G11: =SUMIFS(月營運明細!$H$2:$H$643,月營運明細!$B$2:$B$643,$A11,月營運明細!$D$2:$D$643,$B11) -> 366 | H11: =SUMIFS(月營運明細!$J$2:$J$643,月營運明細!$B$2:$B$643,$A11,月營運明細!$D$2:$D$643,$B11) -> 18945000 | I11: =SUMIFS(月營運明細!$R$2:$R$643,月營運明細!$B$2:$B$643,$A11,月營運明細!$D$2:$D$643,$B11) -> 16185569 | J11: =H11-I11 -> 2759431 | K11: =IF(H11=0,0,J11/H11) -> 0.14565484 | L11: =SUMIFS(月營運明細!$K$2:$K$643,月營運明細!$B$2:$B$643,$A11,月營運明細!$D$2:$D$643,$B11) -> 67205 | M11: =IF(L11=0,0,H11/L11) -> 281.89867 | N11: =IF(G11=0,0,H11/G11) -> 51762.295 | O11: =IF(H11=0,0,SUMIFS(月營運明細!$L$2:$L$643,月營運明細!$B$2:$B$643,$A11,月營運明細!$D$2:$D$643,$B11)/H11) -> 0.32503563 | P11: =IF(H11=0,0,SUMIFS(月營運明細!$M$2:$M$643,月營運明細!$B$2:$B$643,$A11,月營運明細!$D$2:$D$643,$B11)/H11) -> 0.25344946 | Q11: =IF(H11=0,0,SUMIFS(月營運明細!$Q$2:$Q$643,月營運明細!$B$2:$B$643,$A11,月營運明細!$D$2:$D$643,$B11)/H11) -> 0.13045495 | R11: =IF(H11=0,0,SUMIFS(通路月營運!$I$2:$I$2509,通路月營運!$B$2:$B$2509,$A11,通路月營運!$D$2:$D$2509,$B11,通路月營運!$H$2:$H$2509,"外送平台")/H11) -> 0.39531803
A12: 2024 | B12: TN01 | C12: =INDEX(門市主檔!$B$2:$B$25,MATCH($B12,門市主檔!$A$2:$A$25,0)) -> 台南中西店 | D12: =INDEX(門市主檔!$C$2:$C$25,MATCH($B12,門市主檔!$A$2:$A$25,0)) -> 南區 | E12: =INDEX(門市主檔!$E$2:$E$25,MATCH($B12,門市主檔!$A$2:$A$25,0)) -> 標準店 | F12: =COUNTIFS(月營運明細!$B$2:$B$643,$A12,月營運明細!$D$2:$D$643,$B12) -> 12 | G12: =SUMIFS(月營運明細!$H$2:$H$643,月營運明細!$B$2:$B$643,$A12,月營運明細!$D$2:$D$643,$B12) -> 366 | H12: =SUMIFS(月營運明細!$J$2:$J$643,月營運明細!$B$2:$B$643,$A12,月營運明細!$D$2:$D$643,$B12) -> 20267500 | I12: =SUMIFS(月營運明細!$R$2:$R$643,月營運明細!$B$2:$B$643,$A12,月營運明細!$D$2:$D$643,$B12) -> 18118416 | J12: =H12-I12 -> 2149084 | K12: =IF(H12=0,0,J12/H12) -> 0.10603597 | L12: =SUMIFS(月營運明細!$K$2:$K$643,月營運明細!$B$2:$B$643,$A12,月營運明細!$D$2:$D$643,$B12) -> 71214 | M12: =IF(L12=0,0,H12/L12) -> 284.59994 | N12: =IF(G12=0,0,H12/G12) -> 55375.683 | O12: =IF(H12=0,0,SUMIFS(月營運明細!$L$2:$L$643,月營運明細!$B$2:$B$643,$A12,月營運明細!$D$2:$D$643,$B12)/H12) -> 0.32113976 | P12: =IF(H12=0,0,SUMIFS(月營運明細!$M$2:$M$643,月營運明細!$B$2:$B$643,$A12,月營運明細!$D$2:$D$643,$B12)/H12) -> 0.25826076 | Q12: =IF(H12=0,0,SUMIFS(月營運明細!$Q$2:$Q$643,月營運明細!$B$2:$B$643,$A12,月營運明細!$D$2:$D$643,$B12)/H12) -> 0.10689607 | R12: =IF(H12=0,0,SUMIFS(通路月營運!$I$2:$I$2509,通路月營運!$B$2:$B$2509,$A12,通路月營運!$D$2:$D$2509,$B12,通路月營運!$H$2:$H$2509,"外送平台")/H12) -> 0.32392747
A13: 2024 | B13: TN02 | C13: =INDEX(門市主檔!$B$2:$B$25,MATCH($B13,門市主檔!$A$2:$A$25,0)) -> 台南東寧店 | D13: =INDEX(門市主檔!$C$2:$C$25,MATCH($B13,門市主檔!$A$2:$A$25,0)) -> 南區 | E13: =INDEX(門市主檔!$E$2:$E$25,MATCH($B13,門市主檔!$A$2:$A$25,0)) -> 小型店 | F13: =COUNTIFS(月營運明細!$B$2:$B$643,$A13,月營運明細!$D$2:$D$643,$B13) -> 12 | G13: =SUMIFS(月營運明細!$H$2:$H$643,月營運明細!$B$2:$B$643,$A13,月營運明細!$D$2:$D$643,$B13) -> 366 | H13: =SUMIFS(月營運明細!$J$2:$J$643,月營運明細!$B$2:$B$643,$A13,月營運明細!$D$2:$D$643,$B13) -> 16593900 | I13: =SUMIFS(月營運明細!$R$2:$R$643,月營運明細!$B$2:$B$643,$A13,月營運明細!$D$2:$D$643,$B13) -> 14247830 | J13: =H13-I13 -> 2346070 | K13: =IF(H13=0,0,J13/H13) -> 0.14138147 | L13: =SUMIFS(月營運明細!$K$2:$K$643,月營運明細!$B$2:$B$643,$A13,月營運明細!$D$2:$D$643,$B13) -> 58725 | M13: =IF(L13=0,0,H13/L13) -> 282.5696 | N13: =IF(G13=0,0,H13/G13) -> 45338.525 | O13: =IF(H13=0,0,SUMIFS(月營運明細!$L$2:$L$643,月營運明細!$B$2:$B$643,$A13,月營運明細!$D$2:$D$643,$B13)/H13) -> 0.3254931 | P13: =IF(H13=0,0,SUMIFS(月營運明細!$M$2:$M$643,月營運明細!$B$2:$B$643,$A13,月營運明細!$D$2:$D$643,$B13)/H13) -> 0.25630503 | Q13: =IF(H13=0,0,SUMIFS(月營運明細!$Q$2:$Q$643,月營運明細!$B$2:$B$643,$A13,月營運明細!$D$2:$D$643,$B13)/H13) -> 0.13167067 | R13: =IF(H13=0,0,SUMIFS(通路月營運!$I$2:$I$2509,通路月營運!$B$2:$B$2509,$A13,通路月營運!$D$2:$D$2509,$B13,通路月營運!$H$2:$H$2509,"外送平台")/H13) -> 0.39900204
... A63: 2026 | B63: YL01 | C63: =INDEX(門市主檔!$B$2:$B$25,MATCH($B63,門市主檔!$A$2:$A$25,0)) -> 雲林斗六店 | D63: =INDEX(門市主檔!$C$2:$C$25,MATCH($B63,門市主檔!$A$2:$A$25,0)) -> 中區 | E63: =INDEX(門市主檔!$E$2:$E$25,MATCH($B63,門市主檔!$A$2:$A$25,0)) -> 標準店 | F63: =COUNTIFS(月營運明細!$B$2:$B$643,$A63,月營運明細!$D$2:$D$643,$B63) -> 9 | G63: =SUMIFS(月營運明細!$H$2:$H$643,月營運明細!$B$2:$B$643,$A63,月營運明細!$D$2:$D$643,$B63) -> 273 | H63: =SUMIFS(月營運明細!$J$2:$J$643,月營運明細!$B$2:$B$643,$A63,月營運明細!$D$2:$D$643,$B63) -> 14896300 | I63: =SUMIFS(月營運明細!$R$2:$R$643,月營運明細!$B$2:$B$643,$A63,月營運明細!$D$2:$D$643,$B63) -> 13121195 | J63: =H63-I63 -> 1775105 | K63: =IF(H63=0,0,J63/H63) -> 0.11916415 | L63: =SUMIFS(月營運明細!$K$2:$K$643,月營運明細!$B$2:$B$643,$A63,月營運明細!$D$2:$D$643,$B63) -> 51733 | M63: =IF(L63=0,0,H63/L63) -> 287.9458 | N63: =IF(G63=0,0,H63/G63) -> 54565.201 | O63: =IF(H63=0,0,SUMIFS(月營運明細!$L$2:$L$643,月營運明細!$B$2:$B$643,$A63,月營運明細!$D$2:$D$643,$B63)/H63) -> 0.32151608 | P63: =IF(H63=0,0,SUMIFS(月營運明細!$M$2:$M$643,月營運明細!$B$2:$B$643,$A63,月營運明細!$D$2:$D$643,$B63)/H63) -> 0.26322644 | Q63: =IF(H63=0,0,SUMIFS(月營運明細!$Q$2:$Q$643,月營運明細!$B$2:$B$643,$A63,月營運明細!$D$2:$D$643,$B63)/H63) -> 0.11466572 | R63: =IF(H63=0,0,SUMIFS(通路月營運!$I$2:$I$2509,通路月營運!$B$2:$B$2509,$A63,通路月營運!$D$2:$D$2509,$B63,通路月營運!$H$2:$H$2509,"外送平台")/H63) -> 0.33236441

Sheet 月度彙總
A1: 年月 | B1: 年 | C1: 月 | D1: 營業門市數 | E1: 營業額 | F1: 總成本 | G1: 營業利益 | H1: 營業利益率 | I1: 來客數 | J1: 平均客單價 | K1: 單店平均營業額 | L1: 外送營業額 | M1: 外送營收佔比 | N1: 營業額月增率 | O1: 營業額年增率
A2: =月曆參數!A2 -> 2024-01 | B2: =月曆參數!B2 -> 2024 | C2: =月曆參數!C2 -> 1 | D2: =COUNTIFS(月營運明細!$A$2:$A$643,$A2) -> 17 | E2: =SUMIFS(月營運明細!$J$2:$J$643,月營運明細!$A$2:$A$643,$A2) -> 23007900 | F2: =SUMIFS(月營運明細!$R$2:$R$643,月營運明細!$A$2:$A$643,$A2) -> 22158970 | G2: =E2-F2 -> 848930 | H2: =IF(E2=0,0,G2/E2) -> 0.036897327 | I2: =SUMIFS(月營運明細!$K$2:$K$643,月營運明細!$A$2:$A$643,$A2) -> 81096 | J2: =IF(I2=0,0,E2/I2) -> 283.7119 | K2: =IF(D2=0,0,E2/D2) -> 1353405.9 | L2: =SUMIFS(通路月營運!$I$2:$I$2509,通路月營運!$A$2:$A$2509,$A2,通路月營運!$H$2:$H$2509,"外送平台") -> 7809000 | M2: =IF(E2=0,0,L2/E2) -> 0.33940516
A3: =月曆參數!A3 -> 2024-02 | B3: =月曆參數!B3 -> 2024 | C3: =月曆參數!C3 -> 2 | D3: =COUNTIFS(月營運明細!$A$2:$A$643,$A3) -> 17 | E3: =SUMIFS(月營運明細!$J$2:$J$643,月營運明細!$A$2:$A$643,$A3) -> 26673100 | F3: =SUMIFS(月營運明細!$R$2:$R$643,月營運明細!$A$2:$A$643,$A3) -> 25188872 | G3: =E3-F3 -> 1484228 | H3: =IF(E3=0,0,G3/E3) -> 0.055645126 | I3: =SUMIFS(月營運明細!$K$2:$K$643,月營運明細!$A$2:$A$643,$A3) -> 93799 | J3: =IF(I3=0,0,E3/I3) -> 284.36444 | K3: =IF(D3=0,0,E3/D3) -> 1569005.9 | L3: =SUMIFS(通路月營運!$I$2:$I$2509,通路月營運!$A$2:$A$2509,$A3,通路月營運!$H$2:$H$2509,"外送平台") -> 9098400 | M3: =IF(E3=0,0,L3/E3) -> 0.34110771 | N3: =IF(E2=0,0,E3/E2-1) -> 0.15930181
A4: =月曆參數!A4 -> 2024-03 | B4: =月曆參數!B4 -> 2024 | C4: =月曆參數!C4 -> 3 | D4: =COUNTIFS(月營運明細!$A$2:$A$643,$A4) -> 17 | E4: =SUMIFS(月營運明細!$J$2:$J$643,月營運明細!$A$2:$A$643,$A4) -> 28505800 | F4: =SUMIFS(月營運明細!$R$2:$R$643,月營運明細!$A$2:$A$643,$A4) -> 25992185 | G4: =E4-F4 -> 2513615 | H4: =IF(E4=0,0,G4/E4) -> 0.088179072 | I4: =SUMIFS(月營運明細!$K$2:$K$643,月營運明細!$A$2:$A$643,$A4) -> 99927 | J4: =IF(I4=0,0,E4/I4) -> 285.26624 | K4: =IF(D4=0,0,E4/D4) -> 1676811.8 | L4: =SUMIFS(通路月營運!$I$2:$I$2509,通路月營運!$A$2:$A$2509,$A4,通路月營運!$H$2:$H$2509,"外送平台") -> 9544500 | M4: =IF(E4=0,0,L4/E4) -> 0.3348266 | N4: =IF(E3=0,0,E4/E3-1) -> 0.068709674
A5: =月曆參數!A5 -> 2024-04 | B5: =月曆參數!B5 -> 2024 | C5: =月曆參數!C5 -> 4 | D5: =COUNTIFS(月營運明細!$A$2:$A$643,$A5) -> 18 | E5: =SUMIFS(月營運明細!$J$2:$J$643,月營運明細!$A$2:$A$643,$A5) -> 31634100 | F5: =SUMIFS(月營運明細!$R$2:$R$643,月營運明細!$A$2:$A$643,$A5) -> 28722330 | G5: =E5-F5 -> 2911770 | H5: =IF(E5=0,0,G5/E5) -> 0.092045293 | I5: =SUMIFS(月營運明細!$K$2:$K$643,月營運明細!$A$2:$A$643,$A5) -> 109674 | J5: =IF(I5=0,0,E5/I5) -> 288.43755 | K5: =IF(D5=0,0,E5/D5) -> 1757450 | L5: =SUMIFS(通路月營運!$I$2:$I$2509,通路月營運!$A$2:$A$2509,$A5,通路月營運!$H$2:$H$2509,"外送平台") -> 10591000 | M5: =IF(E5=0,0,L5/E5) -> 0.33479694 | N5: =IF(E4=0,0,E5/E4-1) -> 0.10974258
A6: =月曆參數!A6 -> 2024-05 | B6: =月曆參數!B6 -> 2024 | C6: =月曆參數!C6 -> 5 | D6: =COUNTIFS(月營運明細!$A$2:$A$643,$A6) -> 18 | E6: =SUMIFS(月營運明細!$J$2:$J$643,月營運明細!$A$2:$A$643,$A6) -> 34150300 | F6: =SUMIFS(月營運明細!$R$2:$R$643,月營運明細!$A$2:$A$643,$A6) -> 30633061 | G6: =E6-F6 -> 3517239 | H6: =IF(E6=0,0,G6/E6) -> 0.10299292 | I6: =SUMIFS(月營運明細!$K$2:$K$643,月營運明細!$A$2:$A$643,$A6) -> 118595 | J6: =IF(I6=0,0,E6/I6) -> 287.95733 | K6: =IF(D6=0,0,E6/D6) -> 1897238.9 | L6: =SUMIFS(通路月營運!$I$2:$I$2509,通路月營運!$A$2:$A$2509,$A6,通路月營運!$H$2:$H$2509,"外送平台") -> 11601700 | M6: =IF(E6=0,0,L6/E6) -> 0.33972469 | N6: =IF(E5=0,0,E6/E5-1) -> 0.079540749
A7: =月曆參數!A7 -> 2024-06 | B7: =月曆參數!B7 -> 2024 | C7: =月曆參數!C7 -> 6 | D7: =COUNTIFS(月營運明細!$A$2:$A$643,$A7) -> 18 | E7: =SUMIFS(月營運明細!$J$2:$J$643,月營運明細!$A$2:$A$643,$A7) -> 33775900 | F7: =SUMIFS(月營運明細!$R$2:$R$643,月營運明細!$A$2:$A$643,$A7) -> 30503128 | G7: =E7-F7 -> 3272772 | H7: =IF(E7=0,0,G7/E7) -> 0.096896663 | I7: =SUMIFS(月營運明細!$K$2:$K$643,月營運明細!$A$2:$A$643,$A7) -> 118620 | J7: =IF(I7=0,0,E7/I7) -> 284.74035 | K7: =IF(D7=0,0,E7/D7) -> 1876438.9 | L7: =SUMIFS(通路月營運!$I$2:$I$2509,通路月營運!$A$2:$A$2509,$A7,通路月營運!$H$2:$H$2509,"外送平台") -> 11301600 | M7: =IF(E7=0,0,L7/E7) -> 0.33460544 | N7: =IF(E6=0,0,E7/E6-1) -> -0.0109633
A8: =月曆參數!A8 -> 2024-07 | B8: =月曆參數!B8 -> 2024 | C8: =月曆參數!C8 -> 7 | D8: =COUNTIFS(月營運明細!$A$2:$A$643,$A8) -> 18 | E8: =SUMIFS(月營運明細!$J$2:$J$643,月營運明細!$A$2:$A$643,$A8) -> 38392700 | F8: =SUMIFS(月營運明細!$R$2:$R$643,月營運明細!$A$2:$A$643,$A8) -> 34585880 | G8: =E8-F8 -> 3806820 | H8: =IF(E8=0,0,G8/E8) -> 0.099154787 | I8: =SUMIFS(月營運明細!$K$2:$K$643,月營運明細!$A$2:$A$643,$A8) -> 131570 | J8: =IF(I8=0,0,E8/I8) -> 291.80436 | K8: =IF(D8=0,0,E8/D8) -> 2132927.8 | L8: =SUMIFS(通路月營運!$I$2:$I$2509,通路月營運!$A$2:$A$2509,$A8,通路月營運!$H$2:$H$2509,"外送平台") -> 13026000 | M8: =IF(E8=0,0,L8/E8) -> 0.33928325 | N8: =IF(E7=0,0,E8/E7-1) -> 0.13668918
A9: =月曆參數!A9 -> 2024-08 | B9: =月曆參數!B9 -> 2024 | C9: =月曆參數!C9 -> 8 | D9: =COUNTIFS(月營運明細!$A$2:$A$643,$A9) -> 18 | E9: =SUMIFS(月營運明細!$J$2:$J$643,月營運明細!$A$2:$A$643,$A9) -> 39496700 | F9: =SUMIFS(月營運明細!$R$2:$R$643,月營運明細!$A$2:$A$643,$A9) -> 35014679 | G9: =E9-F9 -> 4482021 | H9: =IF(E9=0,0,G9/E9) -> 0.11347837 | I9: =SUMIFS(月營運明細!$K$2:$K$643,月營運明細!$A$2:$A$643,$A9) -> 136478 | J9: =IF(I9=0,0,E9/I9) -> 289.39976 | K9: =IF(D9=0,0,E9/D9) -> 2194261.1 | L9: =SUMIFS(通路月營運!$I$2:$I$2509,通路月營運!$A$2:$A$2509,$A9,通路月營運!$H$2:$H$2509,"外送平台") -> 13306300 | M9: =IF(E9=0,0,L9/E9) -> 0.3368965 | N9: =IF(E8=0,0,E9/E8-1) -> 0.028755467
A10: =月曆參數!A10 -> 2024-09 | B10: =月曆參數!B10 -> 2024 | C10: =月曆參數!C10 -> 9 | D10: =COUNTIFS(月營運明細!$A$2:$A$643,$A10) -> 19 | E10: =SUMIFS(月營運明細!$J$2:$J$643,月營運明細!$A$2:$A$643,$A10) -> 35096000 | F10: =SUMIFS(月營運明細!$R$2:$R$643,月營運明細!$A$2:$A$643,$A10) -> 31891981 | G10: =E10-F10 -> 3204019 | H10: =IF(E10=0,0,G10/E10) -> 0.091292996 | I10: =SUMIFS(月營運明細!$K$2:$K$643,月營運明細!$A$2:$A$643,$A10) -> 123545 | J10: =IF(I10=0,0,E10/I10) -> 284.07463 | K10: =IF(D10=0,0,E10/D10) -> 1847157.9 | L10: =SUMIFS(通路月營運!$I$2:$I$2509,通路月營運!$A$2:$A$2509,$A10,通路月營運!$H$2:$H$2509,"外送平台") -> 11805700 | M10: =IF(E10=0,0,L10/E10) -> 0.33638306 | N10: =IF(E9=0,0,E10/E9-1) -> -0.11141944
A11: =月曆參數!A11 -> 2024-10 | B11: =月曆參數!B11 -> 2024 | C11: =月曆參數!C11 -> 10 | D11: =COUNTIFS(月營運明細!$A$2:$A$643,$A11) -> 19 | E11: =SUMIFS(月營運明細!$J$2:$J$643,月營運明細!$A$2:$A$643,$A11) -> 37075700 | F11: =SUMIFS(月營運明細!$R$2:$R$643,月營運明細!$A$2:$A$643,$A11) -> 33205617 | G11: =E11-F11 -> 3870083 | H11: =IF(E11=0,0,G11/E11) -> 0.10438328 | I11: =SUMIFS(月營運明細!$K$2:$K$643,月營運明細!$A$2:$A$643,$A11) -> 127751 | J11: =IF(I11=0,0,E11/I11) -> 290.21847 | K11: =IF(D11=0,0,E11/D11) -> 1951352.6 | L11: =SUMIFS(通路月營運!$I$2:$I$2509,通路月營運!$A$2:$A$2509,$A11,通路月營運!$H$2:$H$2509,"外送平台") -> 12564900 | M11: =IF(E11=0,0,L11/E11) -> 0.33889852 | N11: =IF(E10=0,0,E11/E10-1) -> 0.056408138
A12: =月曆參數!A12 -> 2024-11 | B12: =月曆參數!B12 -> 2024 | C12: =月曆參數!C12 -> 11 | D12: =COUNTIFS(月營運明細!$A$2:$A$643,$A12) -> 19 | E12: =SUMIFS(月營運明細!$J$2:$J$643,月營運明細!$A$2:$A$643,$A12) -> 36409200 | F12: =SUMIFS(月營運明細!$R$2:$R$643,月營運明細!$A$2:$A$643,$A12) -> 32750229 | G12: =E12-F12 -> 3658971 | H12: =IF(E12=0,0,G12/E12) -> 0.10049578 | I12: =SUMIFS(月營運明細!$K$2:$K$643,月營運明細!$A$2:$A$643,$A12) -> 125624 | J12: =IF(I12=0,0,E12/I12) -> 289.82678 | K12: =IF(D12=0,0,E12/D12) -> 1916273.7 | L12: =SUMIFS(通路月營運!$I$2:$I$2509,通路月營運!$A$2:$A$2509,$A12,通路月營運!$H$2:$H$2509,"外送平台") -> 12341300 | M12: =IF(E12=0,0,L12/E12) -> 0.33896103 | N12: =IF(E11=0,0,E12/E11-1) -> -0.017976734
A13: =月曆參數!A13 -> 2024-12 | B13: =月曆參數!B13 -> 2024 | C13: =月曆參數!C13 -> 12 | D13: =COUNTIFS(月營運明細!$A$2:$A$643,$A13) -> 18 | E13: =SUMIFS(月營運明細!$J$2:$J$643,月營運明細!$A$2:$A$643,$A13) -> 41478400 | F13: =SUMIFS(月營運明細!$R$2:$R$643,月營運明細!$A$2:$A$643,$A13) -> 36629339 | G13: =E13-F13 -> 4849061 | H13: =IF(E13=0,0,G13/E13) -> 0.11690569 | I13: =SUMIFS(月營運明細!$K$2:$K$643,月營運明細!$A$2:$A$643,$A13) -> 144108 | J13: =IF(I13=0,0,E13/I13) -> 287.82857 | K13: =IF(D13=0,0,E13/D13) -> 2304355.6 | L13: =SUMIFS(通路月營運!$I$2:$I$2509,通路月營運!$A$2:$A$2509,$A13,通路月營運!$H$2:$H$2509,"外送平台") -> 13828300 | M13: =IF(E13=0,0,L13/E13) -> 0.33338557 | N13: =IF(E12=0,0,E13/E12-1) -> 0.13922855
A14: =月曆參數!A14 -> 2025-01 | B14: =月曆參數!B14 -> 2025 | C14: =月曆參數!C14 -> 1 | D14: =COUNTIFS(月營運明細!$A$2:$A$643,$A14) -> 18 | E14: =SUMIFS(月營運明細!$J$2:$J$643,月營運明細!$A$2:$A$643,$A14) -> 42768000 | F14: =SUMIFS(月營運明細!$R$2:$R$643,月營運明細!$A$2:$A$643,$A14) -> 38042320 | G14: =E14-F14 -> 4725680 | H14: =IF(E14=0,0,G14/E14) -> 0.1104957 | I14: =SUMIFS(月營運明細!$K$2:$K$643,月營運明細!$A$2:$A$643,$A14) -> 151548 | J14: =IF(I14=0,0,E14/I14) -> 282.20762 | K14: =IF(D14=0,0,E14/D14) -> 2376000 | L14: =SUMIFS(通路月營運!$I$2:$I$2509,通路月營運!$A$2:$A$2509,$A14,通路月營運!$H$2:$H$2509,"外送平台") -> 14303000 | M14: =IF(E14=0,0,L14/E14) -> 0.33443229 | N14: =IF(E13=0,0,E14/E13-1) -> 0.031090881 | O14: =IF(E2=0,0,E14/E2-1) -> 0.85883979
A15: =月曆參數!A15 -> 2025-02 | B15: =月曆參數!B15 -> 2025 | C15: =月曆參數!C15 -> 2 | D15: =COUNTIFS(月營運明細!$A$2:$A$643,$A15) -> 19 | E15: =SUMIFS(月營運明細!$J$2:$J$643,月營運明細!$A$2:$A$643,$A15) -> 37338300 | F15: =SUMIFS(月營運明細!$R$2:$R$643,月營運明細!$A$2:$A$643,$A15) -> 33618034 | G15: =E15-F15 -> 3720266 | H15: =IF(E15=0,0,G15/E15) -> 0.099636727 | I15: =SUMIFS(月營運明細!$K$2:$K$643,月營運明細!$A$2:$A$643,$A15) -> 130409 | J15: =IF(I15=0,0,E15/I15) -> 286.3169 | K15: =IF(D15=0,0,E15/D15) -> 1965173.7 | L15: =SUMIFS(通路月營運!$I$2:$I$2509,通路月營運!$A$2:$A$2509,$A15,通路月營運!$H$2:$H$2509,"外送平台") -> 12525100 | M15: =IF(E15=0,0,L15/E15) -> 0.33544912 | N15: =IF(E14=0,0,E15/E14-1) -> -0.12695707 | O15: =IF(E3=0,0,E15/E3-1) -> 0.39984854
A16: =月曆參數!A16 -> 2025-03 | B16: =月曆參數!B16 -> 2025 | C16: =月曆參數!C16 -> 3 | D16: =COUNTIFS(月營運明細!$A$2:$A$643,$A16) -> 19 | E16: =SUMIFS(月營運明細!$J$2:$J$643,月營運明細!$A$2:$A$643,$A16) -> 36335800 | F16: =SUMIFS(月營運明細!$R$2:$R$643,月營運明細!$A$2:$A$643,$A16) -> 32761196 | G16: =E16-F16 -> 3574604 | H16: =IF(E16=0,0,G16/E16) -> 0.098376918 | I16: =SUMIFS(月營運明細!$K$2:$K$643,月營運明細!$A$2:$A$643,$A16) -> 128458 | J16: =IF(I16=0,0,E16/I16) -> 282.86132 | K16: =IF(D16=0,0,E16/D16) -> 1912410.5 | L16: =SUMIFS(通路月營運!$I$2:$I$2509,通路月營運!$A$2:$A$2509,$A16,通路月營運!$H$2:$H$2509,"外送平台") -> 12319400 | M16: =IF(E16=0,0,L16/E16) -> 0.33904304 | N16: =IF(E15=0,0,E16/E15-1) -> -0.026849107 | O16: =IF(E4=0,0,E16/E4-1) -> 0.27468094
A17: =月曆參數!A17 -> 2025-04 | B17: =月曆參數!B17 -> 2025 | C17: =月曆參數!C17 -> 4 | D17: =COUNTIFS(月營運明細!$A$2:$A$643,$A17) -> 19 | E17: =SUMIFS(月營運明細!$J$2:$J$643,月營運明細!$A$2:$A$643,$A17) -> 34990700 | F17: =SUMIFS(月營運明細!$R$2:$R$643,月營運明細!$A$2:$A$643,$A17) -> 32000672 | G17: =E17-F17 -> 2990028 | H17: =IF(E17=0,0,G17/E17) -> 0.085452077 | I17: =SUMIFS(月營運明細!$K$2:$K$643,月營運明細!$A$2:$A$643,$A17) -> 122783 | J17: =IF(I17=0,0,E17/I17) -> 284.98001 | K17: =IF(D17=0,0,E17/D17) -> 1841615.8 | L17: =SUMIFS(通路月營運!$I$2:$I$2509,通路月營運!$A$2:$A$2509,$A17,通路月營運!$H$2:$H$2509,"外送平台") -> 11985800 | M17: =IF(E17=0,0,L17/E17) -> 0.34254245 | N17: =IF(E16=0,0,E17/E16-1) -> -0.037018588 | O17: =IF(E5=0,0,E17/E5-1) -> 0.10610702
A18: =月曆參數!A18 -> 2025-05 | B18: =月曆參數!B18 -> 2025 | C18: =月曆參數!C18 -> 5 | D18: =COUNTIFS(月營運明細!$A$2:$A$643,$A18) -> 19 | E18: =SUMIFS(月營運明細!$J$2:$J$643,月營運明細!$A$2:$A$643,$A18) -> 37113200 | F18: =SUMIFS(月營運明細!$R$2:$R$643,月營運明細!$A$2:$A$643,$A18) -> 33718498 | G18: =E18-F18 -> 3394702 | H18: =IF(E18=0,0,G18/E18) -> 0.091468857 | I18: =SUMIFS(月營運明細!$K$2:$K$643,月營運明細!$A$2:$A$643,$A18) -> 130278 | J18: =IF(I18=0,0,E18/I18) -> 284.87696 | K18: =IF(D18=0,0,E18/D18) -> 1953326.3 | L18: =SUMIFS(通路月營運!$I$2:$I$2509,通路月營運!$A$2:$A$2509,$A18,通路月營運!$H$2:$H$2509,"外送平台") -> 12724700 | M18: =IF(E18=0,0,L18/E18) -> 0.34286184 | N18: =IF(E17=0,0,E18/E17-1) -> 0.060658975 | O18: =IF(E6=0,0,E18/E6-1) -> 0.086760585
A19: =月曆參數!A19 -> 2025-06 | B19: =月曆參數!B19 -> 2025 | C19: =月曆參數!C19 -> 6 | D19: =COUNTIFS(月營運明細!$A$2:$A$643,$A19) -> 19 | E19: =SUMIFS(月營運明細!$J$2:$J$643,月營運明細!$A$2:$A$643,$A19) -> 37222800 | F19: =SUMIFS(月營運明細!$R$2:$R$643,月營運明細!$A$2:$A$643,$A19) -> 33477920 | G19: =E19-F19 -> 3744880 | H19: =IF(E19=0,0,G19/E19) -> 0.10060715 | I19: =SUMIFS(月營運明細!$K$2:$K$643,月營運明細!$A$2:$A$643,$A19) -> 130659 | J19: =IF(I19=0,0,E19/I19) -> 284.88508 | K19: =IF(D19=0,0,E19/D19) -> 1959094.7 | L19: =SUMIFS(通路月營運!$I$2:$I$2509,通路月營運!$A$2:$A$2509,$A19,通路月營運!$H$2:$H$2509,"外送平台") -> 12543000 | M19: =IF(E19=0,0,L19/E19) -> 0.33697089 | N19: =IF(E18=0,0,E19/E18-1) -> 0.0029531272 | O19: =IF(E7=0,0,E19/E7-1) -> 0.10205205
A20: =月曆參數!A20 -> 2025-07 | B20: =月曆參數!B20 -> 2025 | C20: =月曆參數!C20 -> 7 | D20: =COUNTIFS(月營運明細!$A$2:$A$643,$A20) -> 21 | E20: =SUMIFS(月營運明細!$J$2:$J$643,月營運明細!$A$2:$A$643,$A20) -> 42576100 | F20: =SUMIFS(月營運明細!$R$2:$R$643,月營運明細!$A$2:$A$643,$A20) -> 37942466 | G20: =E20-F20 -> 4633634 | H20: =IF(E20=0,0,G20/E20) -> 0.10883181 | I20: =SUMIFS(月營運明細!$K$2:$K$643,月營運明細!$A$2:$A$643,$A20) -> 146134 | J20: =IF(I20=0,0,E20/I20) -> 291.34972 | K20: =IF(D20=0,0,E20/D20) -> 2027433.3 | L20: =SUMIFS(通路月營運!$I$2:$I$2509,通路月營運!$A$2:$A$2509,$A20,通路月營運!$H$2:$H$2509,"外送平台") -> 14624900 | M20: =IF(E20=0,0,L20/E20) -> 0.34350023 | N20: =IF(E19=0,0,E20/E19-1) -> 0.14381777 | O20: =IF(E8=0,0,E20/E8-1) -> 0.10896342
A21: =月曆參數!A21 -> 2025-08 | B21: =月曆參數!B21 -> 2025 | C21: =月曆參數!C21 -> 8 | D21: =COUNTIFS(月營運明細!$A$2:$A$643,$A21) -> 21 | E21: =SUMIFS(月營運明細!$J$2:$J$643,月營運明細!$A$2:$A$643,$A21) -> 45331400 | F21: =SUMIFS(月營運明細!$R$2:$R$643,月營運明細!$A$2:$A$643,$A21) -> 39769940 | G21: =E21-F21 -> 5561460 | H21: =IF(E21=0,0,G21/E21) -> 0.1226845 | I21: =SUMIFS(月營運明細!$K$2:$K$643,月營運明細!$A$2:$A$643,$A21) -> 159600 | J21: =IF(I21=0,0,E21/I21) -> 284.03133 | K21: =IF(D21=0,0,E21/D21) -> 2158638.1 | L21: =SUMIFS(通路月營運!$I$2:$I$2509,通路月營運!$A$2:$A$2509,$A21,通路月營運!$H$2:$H$2509,"外送平台") -> 15676000 | M21: =IF(E21=0,0,L21/E21) -> 0.34580887 | N21: =IF(E20=0,0,E21/E20-1) -> 0.064714711 | O21: =IF(E9=0,0,E21/E9-1) -> 0.14772627
A22: =月曆參數!A22 -> 2025-09 | B22: =月曆參數!B22 -> 2025 | C22: =月曆參數!C22 -> 9 | D22: =COUNTIFS(月營運明細!$A$2:$A$643,$A22) -> 20 | E22: =SUMIFS(月營運明細!$J$2:$J$643,月營運明細!$A$2:$A$643,$A22) -> 39258300 | F22: =SUMIFS(月營運明細!$R$2:$R$643,月營運明細!$A$2:$A$643,$A22) -> 35392404 | G22: =E22-F22 -> 3865896 | H22: =IF(E22=0,0,G22/E22) -> 0.098473342 | I22: =SUMIFS(月營運明細!$K$2:$K$643,月營運明細!$A$2:$A$643,$A22) -> 138654 | J22: =IF(I22=0,0,E22/I22) -> 283.1386 | K22: =IF(D22=0,0,E22/D22) -> 1962915 | L22: =SUMIFS(通路月營運!$I$2:$I$2509,通路月營運!$A$2:$A$2509,$A22,通路月營運!$H$2:$H$2509,"外送平台") -> 13480600 | M22: =IF(E22=0,0,L22/E22) -> 0.34338216 | N22: =IF(E21=0,0,E22/E21-1) -> -0.13397115 | O22: =IF(E10=0,0,E22/E10-1) -> 0.11859756
A23: =月曆參數!A23 -> 2025-10 | B23: =月曆參數!B23 -> 2025 | C23: =月曆參數!C23 -> 10 | D23: =COUNTIFS(月營運明細!$A$2:$A$643,$A23) -> 20 | E23: =SUMIFS(月營運明細!$J$2:$J$643,月營運明細!$A$2:$A$643,$A23) -> 40718800 | F23: =SUMIFS(月營運明細!$R$2:$R$643,月營運明細!$A$2:$A$643,$A23) -> 36450728 | G23: =E23-F23 -> 4268072 | H23: =IF(E23=0,0,G23/E23) -> 0.10481822 | I23: =SUMIFS(月營運明細!$K$2:$K$643,月營運明細!$A$2:$A$643,$A23) -> 144017 | J23: =IF(I23=0,0,E23/I23) -> 282.73607 | K23: =IF(D23=0,0,E23/D23) -> 2035940 | L23: =SUMIFS(通路月營運!$I$2:$I$2509,通路月營運!$A$2:$A$2509,$A23,通路月營運!$H$2:$H$2509,"外送平台") -> 13889200 | M23: =IF(E23=0,0,L23/E23) -> 0.34110043 | N23: =IF(E22=0,0,E23/E22-1) -> 0.037202324 | O23: =IF(E11=0,0,E23/E11-1) -> 0.098261125
A24: =月曆參數!A24 -> 2025-11 | B24: =月曆參數!B24 -> 2025 | C24: =月曆參數!C24 -> 11 | D24: =COUNTIFS(月營運明細!$A$2:$A$643,$A24) -> 20 | E24: =SUMIFS(月營運明細!$J$2:$J$643,月營運明細!$A$2:$A$643,$A24) -> 40890400 | F24: =SUMIFS(月營運明細!$R$2:$R$643,月營運明細!$A$2:$A$643,$A24) -> 36777508 | G24: =E24-F24 -> 4112892 | H24: =IF(E24=0,0,G24/E24) -> 0.10058332 | I24: =SUMIFS(月營運明細!$K$2:$K$643,月營運明細!$A$2:$A$643,$A24) -> 142264 | J24: =IF(I24=0,0,E24/I24) -> 287.42619 | K24: =IF(D24=0,0,E24/D24) -> 2044520 | L24: =SUMIFS(通路月營運!$I$2:$I$2509,通路月營運!$A$2:$A$2509,$A24,通路月營運!$H$2:$H$2509,"外送平台") -> 13976200 | M24: =IF(E24=0,0,L24/E24) -> 0.34179661 | N24: =IF(E23=0,0,E24/E23-1) -> 0.0042142696 | O24: =IF(E12=0,0,E24/E12-1) -> 0.12307878
A25: =月曆參數!A25 -> 2025-12 | B25: =月曆參數!B25 -> 2025 | C25: =月曆參數!C25 -> 12 | D25: =COUNTIFS(月營運明細!$A$2:$A$643,$A25) -> 20 | E25: =SUMIFS(月營運明細!$J$2:$J$643,月營運明細!$A$2:$A$643,$A25) -> 46865500 | F25: =SUMIFS(月營運明細!$R$2:$R$643,月營運明細!$A$2:$A$643,$A25) -> 41225900 | G25: =E25-F25 -> 5639600 | H25: =IF(E25=0,0,G25/E25) -> 0.12033585 | I25: =SUMIFS(月營運明細!$K$2:$K$643,月營運明細!$A$2:$A$643,$A25) -> 162886 | J25: =IF(I25=0,0,E25/I25) -> 287.71963 | K25: =IF(D25=0,0,E25/D25) -> 2343275 | L25: =SUMIFS(通路月營運!$I$2:$I$2509,通路月營運!$A$2:$A$2509,$A25,通路月營運!$H$2:$H$2509,"外送平台") -> 16055000 | M25: =IF(E25=0,0,L25/E25) -> 0.3425761 | N25: =IF(E24=0,0,E25/E24-1) -> 0.14612476 | O25: =IF(E13=0,0,E25/E13-1) -> 0.12987724
... A34: =月曆參數!A34 -> 2026-09 | B34: =月曆參數!B34 -> 2026 | C34: =月曆參數!C34 -> 9 | D34: =COUNTIFS(月營運明細!$A$2:$A$643,$A34) -> 22 | E34: =SUMIFS(月營運明細!$J$2:$J$643,月營運明細!$A$2:$A$643,$A34) -> 43500800 | F34: =SUMIFS(月營運明細!$R$2:$R$643,月營運明細!$A$2:$A$643,$A34) -> 39645239 | G34: =E34-F34 -> 3855561 | H34: =IF(E34=0,0,G34/E34) -> 0.088631956 | I34: =SUMIFS(月營運明細!$K$2:$K$643,月營運明細!$A$2:$A$643,$A34) -> 150854 | J34: =IF(I34=0,0,E34/I34) -> 288.36358 | K34: =IF(D34=0,0,E34/D34) -> 1977309.1 | L34: =SUMIFS(通路月營運!$I$2:$I$2509,通路月營運!$A$2:$A$2509,$A34,通路月營運!$H$2:$H$2509,"外送平台") -> 15066200 | M34: =IF(E34=0,0,L34/E34) -> 0.34634306 | N34: =IF(E33=0,0,E34/E33-1) -> -0.10771067 | O34: =IF(E22=0,0,E34/E22-1) -> 0.10806632

Sheet 年度關鍵指標
A1: 年度 | B1: 指標代碼 | C1: 指標名稱 | D1: 數值 | E1: 單位
A2: 2024 | B2: store_count | C2: 年底營業門市數 | D2: =COUNTIFS(門市年度設定!$A$2:$A$63,$A2) -> 19 | E2: 家
A3: 2025 | B3: store_count | C3: 年底營業門市數 | D3: =COUNTIFS(門市年度設定!$A$2:$A$63,$A3) -> 21 | E3: 家
A4: 2026 | B4: store_count | C4: 年底營業門市數 | D4: =COUNTIFS(門市年度設定!$A$2:$A$63,$A4) -> 22 | E4: 家
A5: 2024 | B5: months_covered | C5: 資料涵蓋月數 | D5: =COUNTIFS(月曆參數!$B$2:$B$34,$A5) -> 12 | E5: 月
A6: 2025 | B6: months_covered | C6: 資料涵蓋月數 | D6: =COUNTIFS(月曆參數!$B$2:$B$34,$A6) -> 12 | E6: 月
A7: 2026 | B7: months_covered | C7: 資料涵蓋月數 | D7: =COUNTIFS(月曆參數!$B$2:$B$34,$A7) -> 9 | E7: 月
A8: 2024 | B8: revenue | C8: 年營業額 | D8: =SUMIFS(月營運明細!$J$2:$J$643,月營運明細!$B$2:$B$643,$A8) -> 405695800 | E8: NT$
A9: 2025 | B9: revenue | C9: 年營業額 | D9: =SUMIFS(月營運明細!$J$2:$J$643,月營運明細!$B$2:$B$643,$A9) -> 481409300 | E9: NT$
A10: 2026 | B10: revenue | C10: 年營業額 | D10: =SUMIFS(月營運明細!$J$2:$J$643,月營運明細!$B$2:$B$643,$A10) -> 388988500 | E10: NT$
A11: 2024 | B11: cost_total | C11: 年總成本 | D11: =SUMIFS(月營運明細!$R$2:$R$643,月營運明細!$B$2:$B$643,$A11) -> 367276271 | E11: NT$
A12: 2025 | B12: cost_total | C12: 年總成本 | D12: =SUMIFS(月營運明細!$R$2:$R$643,月營運明細!$B$2:$B$643,$A12) -> 431177586 | E12: NT$
A13: 2026 | B13: cost_total | C13: 年總成本 | D13: =SUMIFS(月營運明細!$R$2:$R$643,月營運明細!$B$2:$B$643,$A13) -> 350571253 | E13: NT$
A14: 2024 | B14: op_profit | C14: 年營業利益 | D14: =SUMIFS(月營運明細!$S$2:$S$643,月營運明細!$B$2:$B$643,$A14) -> 38419529 | E14: NT$
A15: 2025 | B15: op_profit | C15: 年營業利益 | D15: =SUMIFS(月營運明細!$S$2:$S$643,月營運明細!$B$2:$B$643,$A15) -> 50231714 | E15: NT$
A16: 2026 | B16: op_profit | C16: 年營業利益 | D16: =SUMIFS(月營運明細!$S$2:$S$643,月營運明細!$B$2:$B$643,$A16) -> 38417247 | E16: NT$
A17: 2024 | B17: op_margin | C17: 營業利益率 | D17: =IF(SUMIFS(月營運明細!$J$2:$J$643,月營運明細!$B$2:$B$643,$A17)=0,0,SUMIFS(月營運明細!$S$2:$S$643,月營運明細!$B$2:$B$643,$A17)/SUMIFS(月營運明細!$J$2:$J$643,月營運明細!$B$2:$B$643,$A17)) -> 0.094700337 | E17: 小數
A18: 2025 | B18: op_margin | C18: 營業利益率 | D18: =IF(SUMIFS(月營運明細!$J$2:$J$643,月營運明細!$B$2:$B$643,$A18)=0,0,SUMIFS(月營運明細!$S$2:$S$643,月營運明細!$B$2:$B$643,$A18)/SUMIFS(月營運明細!$J$2:$J$643,月營運明細!$B$2:$B$643,$A18)) -> 0.10434305 | E18: 小數
A19: 2026 | B19: op_margin | C19: 營業利益率 | D19: =IF(SUMIFS(月營運明細!$J$2:$J$643,月營運明細!$B$2:$B$643,$A19)=0,0,SUMIFS(月營運明細!$S$2:$S$643,月營運明細!$B$2:$B$643,$A19)/SUMIFS(月營運明細!$J$2:$J$643,月營運明細!$B$2:$B$643,$A19)) -> 0.098761909 | E19: 小數
A20: 2024 | B20: guests | C20: 年來客數 | D20: =SUMIFS(月營運明細!$K$2:$K$643,月營運明細!$B$2:$B$643,$A20) -> 1410787 | E20: 人次
A21: 2025 | B21: guests | C21: 年來客數 | D21: =SUMIFS(月營運明細!$K$2:$K$643,月營運明細!$B$2:$B$643,$A21) -> 1687690 | E21: 人次
A22: 2026 | B22: guests | C22: 年來客數 | D22: =SUMIFS(月營運明細!$K$2:$K$643,月營運明細!$B$2:$B$643,$A22) -> 1356192 | E22: 人次
A23: 2024 | B23: avg_ticket | C23: 平均客單價 | D23: =IF(SUMIFS(月營運明細!$K$2:$K$643,月營運明細!$B$2:$B$643,$A23)=0,0,SUMIFS(月營運明細!$J$2:$J$643,月營運明細!$B$2:$B$643,$A23)/SUMIFS(月營運明細!$K$2:$K$643,月營運明細!$B$2:$B$643,$A23)) -> 287.56701 | E23: NT$
A24: 2025 | B24: avg_ticket | C24: 平均客單價 | D24: =IF(SUMIFS(月營運明細!$K$2:$K$643,月營運明細!$B$2:$B$643,$A24)=0,0,SUMIFS(月營運明細!$J$2:$J$643,月營運明細!$B$2:$B$643,$A24)/SUMIFS(月營運明細!$K$2:$K$643,月營運明細!$B$2:$B$643,$A24)) -> 285.24747 | E24: NT$
A25: 2026 | B25: avg_ticket | C25: 平均客單價 | D25: =IF(SUMIFS(月營運明細!$K$2:$K$643,月營運明細!$B$2:$B$643,$A25)=0,0,SUMIFS(月營運明細!$J$2:$J$643,月營運明細!$B$2:$B$643,$A25)/SUMIFS(月營運明細!$K$2:$K$643,月營運明細!$B$2:$B$643,$A25)) -> 286.82406 | E25: NT$
A26: 2024 | B26: food_rate | C26: 食材成本率 | D26: =IF(SUMIFS(月營運明細!$J$2:$J$643,月營運明細!$B$2:$B$643,$A26)=0,0,SUMIFS(月營運明細!$L$2:$L$643,月營運明細!$B$2:$B$643,$A26)/SUMIFS(月營運明細!$J$2:$J$643,月營運明細!$B$2:$B$643,$A26)) -> 0.3204221 | E26: 小數
A27: 2025 | B27: food_rate | C27: 食材成本率 | D27: =IF(SUMIFS(月營運明細!$J$2:$J$643,月營運明細!$B$2:$B$643,$A27)=0,0,SUMIFS(月營運明細!$L$2:$L$643,月營運明細!$B$2:$B$643,$A27)/SUMIFS(月營運明細!$J$2:$J$643,月營運明細!$B$2:$B$643,$A27)) -> 0.31919741 | E27: 小數
A28: 2026 | B28: food_rate | C28: 食材成本率 | D28: =IF(SUMIFS(月營運明細!$J$2:$J$643,月營運明細!$B$2:$B$643,$A28)=0,0,SUMIFS(月營運明細!$L$2:$L$643,月營運明細!$B$2:$B$643,$A28)/SUMIFS(月營運明細!$J$2:$J$643,月營運明細!$B$2:$B$643,$A28)) -> 0.32283268 | E28: 小數
A29: 2024 | B29: labor_rate | C29: 人事成本率 | D29: =IF(SUMIFS(月營運明細!$J$2:$J$643,月營運明細!$B$2:$B$643,$A29)=0,0,SUMIFS(月營運明細!$M$2:$M$643,月營運明細!$B$2:$B$643,$A29)/SUMIFS(月營運明細!$J$2:$J$643,月營運明細!$B$2:$B$643,$A29)) -> 0.25808253 | E29: 小數
A30: 2025 | B30: labor_rate | C30: 人事成本率 | D30: =IF(SUMIFS(月營運明細!$J$2:$J$643,月營運明細!$B$2:$B$643,$A30)=0,0,SUMIFS(月營運明細!$M$2:$M$643,月營運明細!$B$2:$B$643,$A30)/SUMIFS(月營運明細!$J$2:$J$643,月營運明細!$B$2:$B$643,$A30)) -> 0.25731368 | E30: 小數
A31: 2026 | B31: labor_rate | C31: 人事成本率 | D31: =IF(SUMIFS(月營運明細!$J$2:$J$643,月營運明細!$B$2:$B$643,$A31)=0,0,SUMIFS(月營運明細!$M$2:$M$643,月營運明細!$B$2:$B$643,$A31)/SUMIFS(月營運明細!$J$2:$J$643,月營運明細!$B$2:$B$643,$A31)) -> 0.2564428 | E31: 小數
A32: 2024 | B32: rent_rate | C32: 租金成本率 | D32: =IF(SUMIFS(月營運明細!$J$2:$J$643,月營運明細!$B$2:$B$643,$A32)=0,0,SUMIFS(月營運明細!$N$2:$N$643,月營運明細!$B$2:$B$643,$A32)/SUMIFS(月營運明細!$J$2:$J$643,月營運明細!$B$2:$B$643,$A32)) -> 0.13193629 | E32: 小數
A33: 2025 | B33: rent_rate | C33: 租金成本率 | D33: =IF(SUMIFS(月營運明細!$J$2:$J$643,月營運明細!$B$2:$B$643,$A33)=0,0,SUMIFS(月營運明細!$N$2:$N$643,月營運明細!$B$2:$B$643,$A33)/SUMIFS(月營運明細!$J$2:$J$643,月營運明細!$B$2:$B$643,$A33)) -> 0.12018671 | E33: 小數
A34: 2026 | B34: rent_rate | C34: 租金成本率 | D34: =IF(SUMIFS(月營運明細!$J$2:$J$643,月營運明細!$B$2:$B$643,$A34)=0,0,SUMIFS(月營運明細!$N$2:$N$643,月營運明細!$B$2:$B$643,$A34)/SUMIFS(月營運明細!$J$2:$J$643,月營運明細!$B$2:$B$643,$A34)) -> 0.1191192 | E34: 小數
A35: 2024 | B35: fee_rate | C35: 外送抽成佔營收比 | D35: =IF(SUMIFS(月營運明細!$J$2:$J$643,月營運明細!$B$2:$B$643,$A35)=0,0,SUMIFS(月營運明細!$Q$2:$Q$643,月營運明細!$B$2:$B$643,$A35)/SUMIFS(月營運明細!$J$2:$J$643,月營運明細!$B$2:$B$643,$A35)) -> 0.1112907 | E35: 小數
A36: 2025 | B36: fee_rate | C36: 外送抽成佔營收比 | D36: =IF(SUMIFS(月營運明細!$J$2:$J$643,月營運明細!$B$2:$B$643,$A36)=0,0,SUMIFS(月營運明細!$Q$2:$Q$643,月營運明細!$B$2:$B$643,$A36)/SUMIFS(月營運明細!$J$2:$J$643,月營運明細!$B$2:$B$643,$A36)) -> 0.11589927 | E36: 小數
A37: 2026 | B37: fee_rate | C37: 外送抽成佔營收比 | D37: =IF(SUMIFS(月營運明細!$J$2:$J$643,月營運明細!$B$2:$B$643,$A37)=0,0,SUMIFS(月營運明細!$Q$2:$Q$643,月營運明細!$B$2:$B$643,$A37)/SUMIFS(月營運明細!$J$2:$J$643,月營運明細!$B$2:$B$643,$A37)) -> 0.12009495 | E37: 小數
A38: 2024 | B38: delivery_share | C38: 外送營收佔比 | D38: =IF(SUMIFS(月營運明細!$J$2:$J$643,月營運明細!$B$2:$B$643,$A38)=0,0,SUMIFS(通路月營運!$I$2:$I$2509,通路月營運!$B$2:$B$2509,$A38,通路月營運!$H$2:$H$2509,"外送平台")/SUMIFS(月營運明細!$J$2:$J$643,月營運明細!$B$2:$B$643,$A38)) -> 0.33724456 | E38: 小數
A39: 2025 | B39: delivery_share | C39: 外送營收佔比 | D39: =IF(SUMIFS(月營運明細!$J$2:$J$643,月營運明細!$B$2:$B$643,$A39)=0,0,SUMIFS(通路月營運!$I$2:$I$2509,通路月營運!$B$2:$B$2509,$A39,通路月營運!$H$2:$H$2509,"外送平台")/SUMIFS(月營運明細!$J$2:$J$643,月營運明細!$B$2:$B$643,$A39)) -> 0.3408802 | E39: 小數
A40: 2026 | B40: delivery_share | C40: 外送營收佔比 | D40: =IF(SUMIFS(月營運明細!$J$2:$J$643,月營運明細!$B$2:$B$643,$A40)=0,0,SUMIFS(通路月營運!$I$2:$I$2509,通路月營運!$B$2:$B$2509,$A40,通路月營運!$H$2:$H$2509,"外送平台")/SUMIFS(月營運明細!$J$2:$J$643,月營運明細!$B$2:$B$643,$A40)) -> 0.34810129 | E40: 小數
A41: 2024 | B41: item_qty | C41: 品項銷售份數合計 | D41: =SUMIFS(品項月銷售!$I$2:$I$6421,品項月銷售!$B$2:$B$6421,$A41) -> 2152742 | E41: 份
A42: 2025 | B42: item_qty | C42: 品項銷售份數合計 | D42: =SUMIFS(品項月銷售!$I$2:$I$6421,品項月銷售!$B$2:$B$6421,$A42) -> 2577896 | E42: 份
A43: 2026 | B43: item_qty | C43: 品項銷售份數合計 | D43: =SUMIFS(品項月銷售!$I$2:$I$6421,品項月銷售!$B$2:$B$6421,$A43) -> 2100116 | E43: 份
A44: 2024 | B44: item_amount | C44: 品項銷售金額合計 | D44: =SUMIFS(品項月銷售!$J$2:$J$6421,品項月銷售!$B$2:$B$6421,$A44) -> 243448735 | E44: NT$
A45: 2025 | B45: item_amount | C45: 品項銷售金額合計 | D45: =SUMIFS(品項月銷售!$J$2:$J$6421,品項月銷售!$B$2:$B$6421,$A45) -> 301296030 | E45: NT$
A46: 2026 | B46: item_amount | C46: 品項銷售金額合計 | D46: =SUMIFS(品項月銷售!$J$2:$J$6421,品項月銷售!$B$2:$B$6421,$A46) -> 252174910 | E46: NT$
A47: 2024 | B47: rev_per_store | C47: 單店平均年營業額 | D47: =IF(COUNTIFS(門市年度設定!$A$2:$A$63,$A47)=0,0,SUMIFS(月營運明細!$J$2:$J$643,月營運明細!$B$2:$B$643,$A47)/COUNTIFS(門市年度設定!$A$2:$A$63,$A47)) -> 21352411 | E47: NT$
A48: 2025 | B48: rev_per_store | C48: 單店平均年營業額 | D48: =IF(COUNTIFS(門市年度設定!$A$2:$A$63,$A48)=0,0,SUMIFS(月營運明細!$J$2:$J$643,月營運明細!$B$2:$B$643,$A48)/COUNTIFS(門市年度設定!$A$2:$A$63,$A48)) -> 22924252 | E48: NT$
A49: 2026 | B49: rev_per_store | C49: 單店平均年營業額 | D49: =IF(COUNTIFS(門市年度設定!$A$2:$A$63,$A49)=0,0,SUMIFS(月營運明細!$J$2:$J$643,月營運明細!$B$2:$B$643,$A49)/COUNTIFS(門市年度設定!$A$2:$A$63,$A49)) -> 17681295 | E49: NT$

Sheet 圖表預覽
A1: 此工作表僅供人工檢視，不含原始資料；自動化流程請略過。
